Workbook

Sheet Synthèse
A1: Façadiers français de 6 à 199 salariés : vérification et dispersion NAF
A2: Données au 24/09/2026, mises à jour le 26/09/2026. Sources : API Recherche d'entreprises (État), INSEE, ADEME (RGE), BODACC, recherche web.
A4: Message clé
A5: • Aucun code NAF ne suffit à cibler les façadiers : le premier (43.99C, maçonnerie) n'en couvre que 34 %, il faut 8 codes pour atteindre 90 %, et ces codes regroupent aussi des maçons, peintres et isolateurs qui ne font pas de façade (dans un test sur 100 entreprises tirées au hasard en 43.99C, seules 26 ont une activité façade, dont 5 en cœur de métier).
A6: • Le nom est un bon filtre, mais il ne suffit pas : 77 à 86 % des entreprises vérifiées dont le nom contient « façade » sont bien des façadiers ; les autres sont menuisiers, étancheurs, échafaudagistes ou plâtriers (en BTP, la « 5e façade » désigne la toiture). Surtout, il rate les façadiers sans ce mot dans leur nom.
A7: • Un ciblage fiable croise plusieurs signaux : qualification RGE « isolation des murs par l'extérieur », site web, activité déclarée au greffe, contrôle web.
A8: • Le statut « actif » du répertoire ne suffit pas : une partie des façadiers confirmés est en liquidation ou en redressement judiciaire d'après le BODACC.
A10: Chiffres clés
A11: Indicateur | B11: Valeur | C11: Précision
A12: Entreprises extraites (actives, 6 à 199 salariés, mot-clé façade / ravalement / bardage) | B12: 629 | C12: Saisi : résultat de l'extraction API du 24/09/2026 (393 + 161 + 89 résultats, doublons retirés).
A13: Exclues par la liste de mots d'exclusion (nettoyage, conseil…) | B13: 4 | C13: Saisi : filtre de l'extraction.
A14: Entreprises analysées | B14: =COUNTA(Base!$A$2:$A$626) -> 625 | C14: Toutes les lignes de l'onglet Base.
A15: Façadiers confirmés | B15: =COUNTIF(Base!$C$2:$C$626,"Confirmé") -> 498 | C15: Preuve d'une activité façade (voir Méthodologie).
A16: dont prospectables (sans alerte juridique) | B16: =COUNTIFS(Base!$C$2:$C$626,"Confirmé",Base!$E$2:$E$626,"") -> 465 | C16: Liste dans l'onglet Prospects.
A17: dont en liquidation ou plan de cession | B17: =COUNTIFS(Base!$C$2:$C$626,"Confirmé",Base!$E$2:$E$626,"NE PAS PROSPECTER*") -> 26 | C17: Source BODACC.
A18: dont en redressement ou sauvegarde récents | B18: =COUNTIFS(Base!$C$2:$C$626,"Confirmé",Base!$E$2:$E$626,"Vigilance*") -> 5 | C18: Procédure ouverte en 2025-2026, vérifiée au BODACC le 26/09/2026.
A19: dont radiés au BODACC | B19: =COUNTIFS(Base!$C$2:$C$626,"Confirmé",Base!$E$2:$E$626,"Radiée*") -> 2
A20: Probables (indices sans preuve directe) | B20: =COUNTIF(Base!$C$2:$C$626,"Probable") -> 64 | C20: Surtout des entreprises « bardage » et « ravalement » restées non vérifiées : quota de 200 recherches web de l'outil d'IA atteint (voir Limites 3).
A21: Douteux (indices d'un autre métier) | B21: =COUNTIF(Base!$C$2:$C$626,"Douteux") -> 26
A22: Hors cible | B22: =COUNTIF(Base!$C$2:$C$626,"Hors cible*") -> 37 | C22: Autre métier, fabricant, bureau d'études, collectivité, commerce…
A23: Codes NAF distincts parmi les façadiers confirmés | B23: ='Dispersion NAF'!$B$4 -> 23 | C23: Voir onglet Dispersion NAF.
A24: Part du 1er code NAF (43.99C) parmi les confirmés | B24: ='Dispersion NAF'!$D$7 -> 0.33534137
A25: Part cumulée des 8 premiers codes NAF (tous en division 43) | B25: ='Dispersion NAF'!$E$14 -> 0.89759036
A26: Taux de confirmation parmi les entreprises vérifiées | B26: =B15/(B14-COUNTIF(Base!$F$2:$F$626,"non vérifié*")) -> 0.8615917 | C26: Confirmés / (analysées − non vérifiées). Par méthode : RGE 100 % (le label vaut preuve), recherche web 77 %, BODACC 81 %.
A28: Façadiers confirmés par spécialité
A29: Spécialité | B29: Nombre | C29: Lecture
A30: Façadier (ravalement, enduits, ITE, bardage) | B30: =COUNTIFS(Base!$C$2:$C$626,"Confirmé",Base!$D$2:$D$626,A30) -> 438 | C30: Catégorie par défaut (confirmés non rangés ailleurs). La spécialité est déduite automatiquement du nom, du NAF et de la preuve : elle est indicative.
A31: Couvreur / étancheur faisant du bardage | B31: =COUNTIFS(Base!$C$2:$C$626,"Confirmé",Base!$D$2:$D$626,A31) -> 43 | C31: Inclus mais à distinguer : le bardage est une activité secondaire de couvreurs.
A32: Façade légère / métallique (murs-rideaux, vêture) | B32: =COUNTIFS(Base!$C$2:$C$626,"Confirmé",Base!$D$2:$D$626,A32) -> 7 | C32: Inclus : métier de l'enveloppe, chantiers et clientèle différents.
A33: Multi-activité (façade parmi d'autres métiers) | B33: =COUNTIFS(Base!$C$2:$C$626,"Confirmé",Base!$D$2:$D$626,A33) -> 10 | C33: Entreprises générales ou peintres faisant aussi de la façade.
A34: Total | B34: =SUM(B30:B33) -> 498 | C34: Égal au nombre de façadiers confirmés.
A36: Périmètre : entreprises actives en France (métropole et DOM), 6 à 199 salariés selon la tranche INSEE, trouvées par la recherche de l'API sur façade, ravalement ou bardage (nom, enseigne ou autres champs : 43 n'ont pas le mot-clé dans leur nom actuel). Lire l'onglet Limites avant toute utilisation des chiffres.

Sheet Dispersion NAF
A1: Dispersion des façadiers confirmés par code NAF
A2: Chaque ligne compte les entreprises classées « Confirmé » dans l'onglet Base (formules).
A4: Codes NAF distincts | B4: =COUNTIF(C7:C29,">0") -> 23
A6: Code NAF | B6: Libellé NAF | C6: Façadiers confirmés | D6: Part | E6: Part cumulée | F6: Cœur de métier | G6: Couvreurs-bardeurs | H6: Façade légère | I6: Multi-activité
A7: 43.99C | B7: Travaux de maçonnerie générale et gros œuvre de bâtiment | C7: =COUNTIFS(Base!$I$2:$I$626,A7,Base!$C$2:$C$626,"Confirmé") -> 167 | D7: =C7/$C$30 -> 0.33534137 | E7: =D7 -> 0.33534137 | F7: =COUNTIFS(Base!$I$2:$I$626,$A7,Base!$C$2:$C$626,"Confirmé",Base!$D$2:$D$626,"Façadier (ravalement, enduits, ITE, bardage)") -> 165 | G7: =COUNTIFS(Base!$I$2:$I$626,$A7,Base!$C$2:$C$626,"Confirmé",Base!$D$2:$D$626,"Couvreur / étancheur faisant du bardage") -> 0 | H7: =COUNTIFS(Base!$I$2:$I$626,$A7,Base!$C$2:$C$626,"Confirmé",Base!$D$2:$D$626,"Façade légère / métallique (murs-rideaux, vêture)") -> 0 | I7: =COUNTIFS(Base!$I$2:$I$626,$A7,Base!$C$2:$C$626,"Confirmé",Base!$D$2:$D$626,"Multi-activité (façade parmi d'autres métiers)") -> 2
A8: 43.34Z | B8: Travaux de peinture et vitrerie | C8: =COUNTIFS(Base!$I$2:$I$626,A8,Base!$C$2:$C$626,"Confirmé") -> 88 | D8: =C8/$C$30 -> 0.17670683 | E8: =E7+D8 -> 0.51204819 | F8: =COUNTIFS(Base!$I$2:$I$626,$A8,Base!$C$2:$C$626,"Confirmé",Base!$D$2:$D$626,"Façadier (ravalement, enduits, ITE, bardage)") -> 86 | G8: =COUNTIFS(Base!$I$2:$I$626,$A8,Base!$C$2:$C$626,"Confirmé",Base!$D$2:$D$626,"Couvreur / étancheur faisant du bardage") -> 0 | H8: =COUNTIFS(Base!$I$2:$I$626,$A8,Base!$C$2:$C$626,"Confirmé",Base!$D$2:$D$626,"Façade légère / métallique (murs-rideaux, vêture)") -> 0 | I8: =COUNTIFS(Base!$I$2:$I$626,$A8,Base!$C$2:$C$626,"Confirmé",Base!$D$2:$D$626,"Multi-activité (façade parmi d'autres métiers)") -> 2
A9: 43.29A | B9: Travaux d'isolation | C9: =COUNTIFS(Base!$I$2:$I$626,A9,Base!$C$2:$C$626,"Confirmé") -> 43 | D9: =C9/$C$30 -> 0.086345382 | E9: =E8+D9 -> 0.59839357 | F9: =COUNTIFS(Base!$I$2:$I$626,$A9,Base!$C$2:$C$626,"Confirmé",Base!$D$2:$D$626,"Façadier (ravalement, enduits, ITE, bardage)") -> 43 | G9: =COUNTIFS(Base!$I$2:$I$626,$A9,Base!$C$2:$C$626,"Confirmé",Base!$D$2:$D$626,"Couvreur / étancheur faisant du bardage") -> 0 | H9: =COUNTIFS(Base!$I$2:$I$626,$A9,Base!$C$2:$C$626,"Confirmé",Base!$D$2:$D$626,"Façade légère / métallique (murs-rideaux, vêture)") -> 0 | I9: =COUNTIFS(Base!$I$2:$I$626,$A9,Base!$C$2:$C$626,"Confirmé",Base!$D$2:$D$626,"Multi-activité (façade parmi d'autres métiers)") -> 0
A10: 43.39Z | B10: Autres travaux de finition | C10: =COUNTIFS(Base!$I$2:$I$626,A10,Base!$C$2:$C$626,"Confirmé") -> 41 | D10: =C10/$C$30 -> 0.082329317 | E10: =E9+D10 -> 0.68072289 | F10: =COUNTIFS(Base!$I$2:$I$626,$A10,Base!$C$2:$C$626,"Confirmé",Base!$D$2:$D$626,"Façadier (ravalement, enduits, ITE, bardage)") -> 40 | G10: =COUNTIFS(Base!$I$2:$I$626,$A10,Base!$C$2:$C$626,"Confirmé",Base!$D$2:$D$626,"Couvreur / étancheur faisant du bardage") -> 0 | H10: =COUNTIFS(Base!$I$2:$I$626,$A10,Base!$C$2:$C$626,"Confirmé",Base!$D$2:$D$626,"Façade légère / métallique (murs-rideaux, vêture)") -> 0 | I10: =COUNTIFS(Base!$I$2:$I$626,$A10,Base!$C$2:$C$626,"Confirmé",Base!$D$2:$D$626,"Multi-activité (façade parmi d'autres métiers)") -> 1
A11: 43.99D | B11: Autres travaux spécialisés de construction | C11: =COUNTIFS(Base!$I$2:$I$626,A11,Base!$C$2:$C$626,"Confirmé") -> 33 | D11: =C11/$C$30 -> 0.06626506 | E11: =E10+D11 -> 0.74698795 | F11: =COUNTIFS(Base!$I$2:$I$626,$A11,Base!$C$2:$C$626,"Confirmé",Base!$D$2:$D$626,"Façadier (ravalement, enduits, ITE, bardage)") -> 33 | G11: =COUNTIFS(Base!$I$2:$I$626,$A11,Base!$C$2:$C$626,"Confirmé",Base!$D$2:$D$626,"Couvreur / étancheur faisant du bardage") -> 0 | H11: =COUNTIFS(Base!$I$2:$I$626,$A11,Base!$C$2:$C$626,"Confirmé",Base!$D$2:$D$626,"Façade légère / métallique (murs-rideaux, vêture)") -> 0 | I11: =COUNTIFS(Base!$I$2:$I$626,$A11,Base!$C$2:$C$626,"Confirmé",Base!$D$2:$D$626,"Multi-activité (façade parmi d'autres métiers)") -> 0
A12: 43.99A | B12: Travaux d'étanchéification | C12: =COUNTIFS(Base!$I$2:$I$626,A12,Base!$C$2:$C$626,"Confirmé") -> 30 | D12: =C12/$C$30 -> 0.060240964 | E12: =E11+D12 -> 0.80722892 | F12: =COUNTIFS(Base!$I$2:$I$626,$A12,Base!$C$2:$C$626,"Confirmé",Base!$D$2:$D$626,"Façadier (ravalement, enduits, ITE, bardage)") -> 12 | G12: =COUNTIFS(Base!$I$2:$I$626,$A12,Base!$C$2:$C$626,"Confirmé",Base!$D$2:$D$626,"Couvreur / étancheur faisant du bardage") -> 18 | H12: =COUNTIFS(Base!$I$2:$I$626,$A12,Base!$C$2:$C$626,"Confirmé",Base!$D$2:$D$626,"Façade légère / métallique (murs-rideaux, vêture)") -> 0 | I12: =COUNTIFS(Base!$I$2:$I$626,$A12,Base!$C$2:$C$626,"Confirmé",Base!$D$2:$D$626,"Multi-activité (façade parmi d'autres métiers)") -> 0
A13: 43.91B | B13: Travaux de couverture par éléments | C13: =COUNTIFS(Base!$I$2:$I$626,A13,Base!$C$2:$C$626,"Confirmé") -> 30 | D13: =C13/$C$30 -> 0.060240964 | E13: =E12+D13 -> 0.86746988 | F13: =COUNTIFS(Base!$I$2:$I$626,$A13,Base!$C$2:$C$626,"Confirmé",Base!$D$2:$D$626,"Façadier (ravalement, enduits, ITE, bardage)") -> 6 | G13: =COUNTIFS(Base!$I$2:$I$626,$A13,Base!$C$2:$C$626,"Confirmé",Base!$D$2:$D$626,"Couvreur / étancheur faisant du bardage") -> 22 | H13: =COUNTIFS(Base!$I$2:$I$626,$A13,Base!$C$2:$C$626,"Confirmé",Base!$D$2:$D$626,"Façade légère / métallique (murs-rideaux, vêture)") -> 0 | I13: =COUNTIFS(Base!$I$2:$I$626,$A13,Base!$C$2:$C$626,"Confirmé",Base!$D$2:$D$626,"Multi-activité (façade parmi d'autres métiers)") -> 2
A14: 43.31Z | B14: Travaux de plâtrerie | C14: =COUNTIFS(Base!$I$2:$I$626,A14,Base!$C$2:$C$626,"Confirmé") -> 15 | D14: =C14/$C$30 -> 0.030120482 | E14: =E13+D14 -> 0.89759036 | F14: =COUNTIFS(Base!$I$2:$I$626,$A14,Base!$C$2:$C$626,"Confirmé",Base!$D$2:$D$626,"Façadier (ravalement, enduits, ITE, bardage)") -> 15 | G14: =COUNTIFS(Base!$I$2:$I$626,$A14,Base!$C$2:$C$626,"Confirmé",Base!$D$2:$D$626,"Couvreur / étancheur faisant du bardage") -> 0 | H14: =COUNTIFS(Base!$I$2:$I$626,$A14,Base!$C$2:$C$626,"Confirmé",Base!$D$2:$D$626,"Façade légère / métallique (murs-rideaux, vêture)") -> 0 | I14: =COUNTIFS(Base!$I$2:$I$626,$A14,Base!$C$2:$C$626,"Confirmé",Base!$D$2:$D$626,"Multi-activité (façade parmi d'autres métiers)") -> 0
A15: 43.33Z | B15: Travaux de revêtement des sols et des murs | C15: =COUNTIFS(Base!$I$2:$I$626,A15,Base!$C$2:$C$626,"Confirmé") -> 14 | D15: =C15/$C$30 -> 0.02811245 | E15: =E14+D15 -> 0.92570281 | F15: =COUNTIFS(Base!$I$2:$I$626,$A15,Base!$C$2:$C$626,"Confirmé",Base!$D$2:$D$626,"Façadier (ravalement, enduits, ITE, bardage)") -> 14 | G15: =COUNTIFS(Base!$I$2:$I$626,$A15,Base!$C$2:$C$626,"Confirmé",Base!$D$2:$D$626,"Couvreur / étancheur faisant du bardage") -> 0 | H15: =COUNTIFS(Base!$I$2:$I$626,$A15,Base!$C$2:$C$626,"Confirmé",Base!$D$2:$D$626,"Façade légère / métallique (murs-rideaux, vêture)") -> 0 | I15: =COUNTIFS(Base!$I$2:$I$626,$A15,Base!$C$2:$C$626,"Confirmé",Base!$D$2:$D$626,"Multi-activité (façade parmi d'autres métiers)") -> 0
A16: 43.32A | B16: Travaux de menuiserie bois et PVC | C16: =COUNTIFS(Base!$I$2:$I$626,A16,Base!$C$2:$C$626,"Confirmé") -> 8 | D16: =C16/$C$30 -> 0.016064257 | E16: =E15+D16 -> 0.94176707 | F16: =COUNTIFS(Base!$I$2:$I$626,$A16,Base!$C$2:$C$626,"Confirmé",Base!$D$2:$D$626,"Façadier (ravalement, enduits, ITE, bardage)") -> 5 | G16: =COUNTIFS(Base!$I$2:$I$626,$A16,Base!$C$2:$C$626,"Confirmé",Base!$D$2:$D$626,"Couvreur / étancheur faisant du bardage") -> 0 | H16: =COUNTIFS(Base!$I$2:$I$626,$A16,Base!$C$2:$C$626,"Confirmé",Base!$D$2:$D$626,"Façade légère / métallique (murs-rideaux, vêture)") -> 3 | I16: =COUNTIFS(Base!$I$2:$I$626,$A16,Base!$C$2:$C$626,"Confirmé",Base!$D$2:$D$626,"Multi-activité (façade parmi d'autres métiers)") -> 0
A17: 41.20A | B17: Construction de maisons individuelles | C17: =COUNTIFS(Base!$I$2:$I$626,A17,Base!$C$2:$C$626,"Confirmé") -> 6 | D17: =C17/$C$30 -> 0.012048193 | E17: =E16+D17 -> 0.95381526 | F17: =COUNTIFS(Base!$I$2:$I$626,$A17,Base!$C$2:$C$626,"Confirmé",Base!$D$2:$D$626,"Façadier (ravalement, enduits, ITE, bardage)") -> 6 | G17: =COUNTIFS(Base!$I$2:$I$626,$A17,Base!$C$2:$C$626,"Confirmé",Base!$D$2:$D$626,"Couvreur / étancheur faisant du bardage") -> 0 | H17: =COUNTIFS(Base!$I$2:$I$626,$A17,Base!$C$2:$C$626,"Confirmé",Base!$D$2:$D$626,"Façade légère / métallique (murs-rideaux, vêture)") -> 0 | I17: =COUNTIFS(Base!$I$2:$I$626,$A17,Base!$C$2:$C$626,"Confirmé",Base!$D$2:$D$626,"Multi-activité (façade parmi d'autres métiers)") -> 0
A18: 41.20B | B18: Construction d'autres bâtiments | C18: =COUNTIFS(Base!$I$2:$I$626,A18,Base!$C$2:$C$626,"Confirmé") -> 4 | D18: =C18/$C$30 -> 0.0080321285 | E18: =E17+D18 -> 0.96184739 | F18: =COUNTIFS(Base!$I$2:$I$626,$A18,Base!$C$2:$C$626,"Confirmé",Base!$D$2:$D$626,"Façadier (ravalement, enduits, ITE, bardage)") -> 3 | G18: =COUNTIFS(Base!$I$2:$I$626,$A18,Base!$C$2:$C$626,"Confirmé",Base!$D$2:$D$626,"Couvreur / étancheur faisant du bardage") -> 0 | H18: =COUNTIFS(Base!$I$2:$I$626,$A18,Base!$C$2:$C$626,"Confirmé",Base!$D$2:$D$626,"Façade légère / métallique (murs-rideaux, vêture)") -> 0 | I18: =COUNTIFS(Base!$I$2:$I$626,$A18,Base!$C$2:$C$626,"Confirmé",Base!$D$2:$D$626,"Multi-activité (façade parmi d'autres métiers)") -> 1
A19: 41.10B | B19: Promotion immobilière de bureaux | C19: =COUNTIFS(Base!$I$2:$I$626,A19,Base!$C$2:$C$626,"Confirmé") -> 3 | D19: =C19/$C$30 -> 0.0060240964 | E19: =E18+D19 -> 0.96787149 | F19: =COUNTIFS(Base!$I$2:$I$626,$A19,Base!$C$2:$C$626,"Confirmé",Base!$D$2:$D$626,"Façadier (ravalement, enduits, ITE, bardage)") -> 3 | G19: =COUNTIFS(Base!$I$2:$I$626,$A19,Base!$C$2:$C$626,"Confirmé",Base!$D$2:$D$626,"Couvreur / étancheur faisant du bardage") -> 0 | H19: =COUNTIFS(Base!$I$2:$I$626,$A19,Base!$C$2:$C$626,"Confirmé",Base!$D$2:$D$626,"Façade légère / métallique (murs-rideaux, vêture)") -> 0 | I19: =COUNTIFS(Base!$I$2:$I$626,$A19,Base!$C$2:$C$626,"Confirmé",Base!$D$2:$D$626,"Multi-activité (façade parmi d'autres métiers)") -> 0
... A29: 43.22A | B29: Travaux d'installation d'eau et de gaz en tous locaux | C29: =COUNTIFS(Base!$I$2:$I$626,A29,Base!$C$2:$C$626,"Confirmé") -> 1 | D29: =C29/$C$30 -> 0.0020080321 | E29: =E28+D29 -> 1 | F29: =COUNTIFS(Base!$I$2:$I$626,$A29,Base!$C$2:$C$626,"Confirmé",Base!$D$2:$D$626,"Façadier (ravalement, enduits, ITE, bardage)") -> 0 | G29: =COUNTIFS(Base!$I$2:$I$626,$A29,Base!$C$2:$C$626,"Confirmé",Base!$D$2:$D$626,"Couvreur / étancheur faisant du bardage") -> 1 | H29: =COUNTIFS(Base!$I$2:$I$626,$A29,Base!$C$2:$C$626,"Confirmé",Base!$D$2:$D$626,"Façade légère / métallique (murs-rideaux, vêture)") -> 0 | I29: =COUNTIFS(Base!$I$2:$I$626,$A29,Base!$C$2:$C$626,"Confirmé",Base!$D$2:$D$626,"Multi-activité (façade parmi d'autres métiers)") -> 0
A30: Total | C30: =SUM(C7:C29) -> 498 | D30: =SUM(D7:D29) -> 1 | F30: =SUM(F7:F29) -> 438 | G30: =SUM(G7:G29) -> 43 | H30: =SUM(H7:H29) -> 7 | I30: =SUM(I7:I29) -> 10
A32: Lecture : 8 codes NAF, tous dans la division 43 (travaux de construction spécialisés), regroupent 90 % des façadiers confirmés ; les 15 autres codes n'en comptent que 51 (10 %). Cibler par NAF a donc deux coûts : manquer environ 10 % des façadiers, classés sous des codes atypiques, et inclure les entreprises de ces 8 codes qui ne font pas de façade. Le premier coût est mesuré ici ; le second est estimé par un test sur un échantillon aléatoire (ligne suivante). Les couvreurs-bardeurs (43.91B, 43.99A) sont sous-représentés : beaucoup n'ont pas pu être vérifiés (voir Limites 3).
A33: Test de précision : sur 100 entreprises tirées au hasard en 43.99C, 26 ont une activité façade, dont 5 seulement en cœur de métier (voir onglet Test précision NAF). Marge d'erreur d'environ ± 8 points.

Sheet Test précision NAF
A1: Test de précision du code NAF 43.99C (maçonnerie générale)
A2: Question : parmi les entreprises classées 43.99C, combien font réellement de la façade ? (voir Limites, ligne 6)
A3: Population : 9 056 entreprises actives de 6 à 199 salariés en 43.99C (API Recherche d'entreprises, 26/09/2026), avec ou sans mot-clé dans le nom.
A4: Tirage : 100 entreprises au hasard, en deux fois (20 puis 80, graines 20260926 et 20260927, reproductibles), toutes vérifiées par un agent IA (Claude). Vérification : même règle que l'onglet Méthodologie (label RGE ADEME, activité déclarée au BODACC, site ou fiche web). Une activité façade trouvée seulement dans un résumé de recherche a été contrôlée sur la page source.
A6: N° | B6: SIREN | C6: Nom | D6: Commune | E6: Effectif (salariés) | F6: Verdict | G6: Preuve | H6: Source
A7: 1 | B7: 336520226 | C7: ROUX CABRERO ENTREPRISE GENERALE DE BATIMENT | D7: ANNONAY (07100) | E7: 20 à 49 | F7: Indice faible (non confirmé) | G7: Entreprise générale de bâtiment (groupe FAYAT). Un annuaire évoque projection de façade et ravalement, mais le site de l'entreprise n'en parle pas. | H7: https://rouxcabrero.fayat.com/
A8: 2 | B8: 879191005 | C8: SARL SEBASTIEN QUERO | D8: BOQUEHO (22170) | E8: 6 à 9 | F8: Indice faible (non confirmé) | G8: Activité déclarée : maçonnerie neuf, terrassement, assainissement, rénovation. Seul un texte générique d'annuaire évoque la restauration de façades en pierre ou brique. | H8: https://omizi.com/professionnel/sarl-sebastien-quero
A9: 3 | B9: 412854184 | C9: A.E.M. CONSTRUCTIONS | D9: PLAISIR (78370) | E9: 10 à 19 | F9: Pas d'activité façade | G9: Activité déclarée : maçonnerie, charpente, couverture, plâtrerie, isolation (fiche PagesJaunes : maçonnerie). | H9: https://www.pagesjaunes.fr/pros/07437598
A10: 4 | B10: 533821484 | C10: BVF 62 (BVF 62) | D10: EPERLECQUES (62910) | E10: 10 à 19 | F10: Pas d'activité façade | G10: Gros œuvre, plâtrerie-isolation, menuiserie, carrelage. RGE isolation intérieure, combles et fenêtres, pas ITE. | H10: https://bvf62.net/
A11: 5 | B11: 316972140 | C11: CONSTRUIRE EN PROVENCE | D11: NYONS (26110) | E11: 10 à 19 | F11: Façade parmi d'autres activités | G11: « démolition, fondation, maçonnerie, béton armé, charpente, couverture, ravalement de façade et isolation » (fiche PagesJaunes). | H11: https://www.pagesjaunes.fr/pros/05573529
A12: 6 | B12: 750188690 | C12: SCA33 | D12: BEYCHAC-ET-CAILLAU (33750) | E12: 10 à 19 | F12: Pas d'activité façade | G12: Activité déclarée : maçonnerie, rénovations, démolitions, terrassements, entretien de routes. | H12: https://annuaire-entreprises.data.gouv.fr/entreprise/sca33-750188690
A13: 7 | B13: 798439287 | C13: CAP CONSTRUCTION MEDITERRANEE | D13: NICE (06200) | E13: 10 à 19 | F13: Pas d'activité façade | G13: Gros œuvre et second œuvre. Liquidation judiciaire le 28/01/2025 (BODACC), alors que le répertoire la donne active. | H13: https://annuaire-entreprises.data.gouv.fr/entreprise/798439287
A14: 8 | B14: 828886093 | C14: N.C.E | D14: GEISPOLSHEIM (67118) | E14: 10 à 19 | F14: Indice faible (non confirmé) | G14: Maçonnerie gros œuvre ; mentionne « maçonnerie de façade » (pierre, brique), pas de ravalement, enduit ni ITE. | H14: https://www.pagesjaunes.fr/pros/58136673
A15: 9 | B15: 402580476 | C15: SARL BRITO ET FILS | D15: VALENCE (26000) | E15: 10 à 19 | F15: Indice faible (non confirmé) | G15: Maçonnerie, carrelage, isolation (fiche PagesJaunes). Un annuaire évoque des travaux de façade, sans confirmation. RGE isolation intérieure uniquement. | H15: https://www.pagesjaunes.fr/pros/07582631
A16: 10 | B16: 442992905 | C16: SARL NONQUE ENTREPRISE MARLIEN | D16: AISEREY (21110) | E16: 10 à 19 | F16: Façade parmi d'autres activités | G16: Qualification RGE « Isolation des murs par l'extérieur » en cours de validité (ADEME), en plus de la maçonnerie. | H16: https://www.france-artisan.fr/annuaire-rge/entreprise/44299290500012
A17: 11 | B17: 517394318 | C17: CORSICA TRAVAUX (CORSICA TRAVAUX) | D17: BIGUGLIA (20620) | E17: 10 à 19 | F17: Pas d'activité façade | G17: Activité déclarée : maintenance et rénovation tous corps d'état (maçonnerie, peinture, plomberie, électricité…). | H17: https://annuaire-entreprises.data.gouv.fr/entreprise/517394318
A18: 12 | B18: 503563025 | C18: AUDET FILS | D18: TARASCON (13150) | E18: 6 à 9 | F18: Pas d'activité façade | G18: Maçonnerie générale, restauration de bâtisses. RGE isolation intérieure, combles et fenêtres, pas ITE. | H18: https://audet-fils.fr/
... A106: 100 | B106: 316806223 | C106: BENAND ET CIE | D106: LA CHAPELLE-D'ABONDANCE (74360) | E106: 6 à 9 | F106: Pas d'activité façade | G106: Maçonnerie, génie civil, terrassement. | H106: https://benand.com/terrassement-enrochement/
A108: Résultat
A109: Entreprises vérifiées | F109: =COUNTA(F7:F106) -> 100
A110: Façadier (cœur de métier) | F110: =COUNTIF(F7:F106,"Façadier (cœur de métier)") -> 5
A111: Façade parmi d'autres activités | F111: =COUNTIF(F7:F106,"Façade parmi d'autres activités") -> 21
A112: Indice faible (non confirmé) | F112: =COUNTIF(F7:F106,"Indice faible (non confirmé)") -> 20
A113: Pas d'activité façade | F113: =COUNTIF(F7:F106,"Pas d'activité façade") -> 54
A114: Part avec une preuve d'activité façade (cœur de métier + parmi d'autres activités) | F114: =(F110+F111)/F109 -> 0.26
A115: Part de façadiers dont c'est le cœur de métier | F115: =F110/F109 -> 0.05
A117: Lecture : 26 entreprises sur 100 ont une activité façade prouvée ; la vraie proportion se situe probablement entre 18 % et 35 % (marge d'environ ± 8 points). Les façadiers de métier sont rares : 5 sur 100. Double vérification : chaque preuve contrôlée sur sa source, 12 « indices faibles » et 12 « pas d'activité » tirés au hasard revus par une seconde recherche.

Sheet Méthodologie
A1: Méthodologie
A2: Chaîne de traitement exécutée le 24/09/2026 avec des scripts Python, puis corrigée et complétée le 26/09/2026 (revérifications, contre-vérifications, test de précision).
A4: Étape | B4: Ce qui est fait | C4: Source | D4: Résultat (entreprises)
A5: 1. Extraction | B5: Recherche des mots-clés « facade », « ravalement », « bardage » ; filtre côté serveur : entreprises actives, tranches d'effectif 6 à 199 salariés. Chaque requête renvoie moins de 400 résultats (393, 161 et 89) : aucune troncature (limite de l'API : 10 000 résultats par requête). | C5: API Recherche d'entreprises (recherche-entreprises.api.gouv.fr) | D5: 629
A6: 2. Exclusions | B6: Retrait des noms contenant des mots hors cible (immobilier, nettoyage, conseil, holding…), en mots entiers. | C6: Règle de l'étude | D6: 4
A7: 3. Libellés NAF | B7: Ajout des libellés officiels de la nomenclature NAF rév. 2. | C7: INSEE | D7: =COUNTA(Base!$A$2:$A$626) -> 625
A8: 4. Vérification automatique | B8: Qualification RGE « isolation des murs par l'extérieur » en cours de validité, ou vocabulaire métier explicite sur le site web déclaré à l'ADEME. | C8: ADEME, liste des entreprises RGE ; sites web | D8: =COUNTIF(Base!$F$2:$F$626,"automatique (RGE*") -> 286
A9: 5. Contrôle web assisté par IA | B9: Recherche nom + commune par un agent IA (Claude, via l'outil de recherche web de Claude Code) ; lecture des résultats et des fiches (site, PagesJaunes, annuaires, objet social) ; verdict motivé avec lien, non relu un par un. Relecture humaine de 20 verdicts tirés au hasard (26/09/2026) : 18 justes (90 %), aucun faux « Confirmé ». Contre-vérification de 20 autres verdicts sur sources primaires (registres officiels, pages des entreprises) : 19 justes (95 %). | C9: Recherche web (agent IA) | D9: =COUNTIF(Base!$F$2:$F$626,"recherche web*") -> 201
A10: 6. Activité déclarée au greffe | B10: Pour les entreprises non contrôlées sur le web : lecture de l'activité déclarée au BODACC (annonces de création et de modification). Le 26/09/2026, la lecture a été étendue aux activités déclarées dans toutes les annonces : 20 entreprises supplémentaires confirmées. | C10: BODACC (API DILA) | D10: =COUNTIF(Base!$F$2:$F$626,"BODACC*") -> 72
A11: 7. Procédures collectives | B11: Dernier jugement significatif (redressement, sauvegarde, liquidation, plan) pour toutes les entreprises. Les procédures antérieures à 2023 ont été revérifiées manuellement sur le BODACC (5 entreprises : 3 réintégrées aux prospects, 1 passée en liquidation). Les 14 entreprises sous plan ou « autre jugement » ont aussi été revérifiées : 2 étaient passées en liquidation (BIG RAVALEMENT, DS RAVALEMENT). | C11: BODACC (API DILA) | D11: =COUNTIF(Base!$P$2:$P$626,"?*") -> 58
A12: 8. Non vérifiées | B12: Entreprises restées sans contrôle web ni activité BODACC exploitable : l'outil de recherche web plafonne à 200 recherches par session, quota atteint. | C12: — | D12: =COUNTIF(Base!$F$2:$F$626,"non vérifié*") -> 47
A13: 9. Classement par NAF seul | B13: NAF hors du bâtiment (restauration, commerce…) : classées hors cible sans recherche web. Les 7 entreprises d'abord exclues pour un NAF « adjacent » ont été revérifiées au BODACC (étape 6) : 6 hors cible, 1 confirmée. | C13: INSEE (code NAF) | D13: =COUNTIF(Base!$F$2:$F$626,"automatique (NAF*") -> 19
A14: Total classées | B14: Étapes 4, 5, 6, 8 et 9 : chaque entreprise est comptée une seule fois. | D14: =D8+D9+D10+D12+D13 -> 625
A15: Règles de classement
A16: Classement | B16: Définition | C16: Exemples de preuves | D16: Nombre
A17: Confirmé | B17: Au moins une preuve explicite d'une activité façade (ravalement, enduits, ITE, bardage, façade légère). | C17: RGE ITE ; site ou fiche décrivant l'activité ; objet social déclaré au greffe. | D17: =COUNTIF(Base!$C$2:$C$626,A17) -> 498
A18: Probable | B18: Nom et NAF cohérents, mais aucune source décrivant le métier (annuaires recopiant le registre), ou entreprise non vérifiée. | C18: Mot-clé dans le nom + NAF du bâtiment. | D18: =COUNTIF(Base!$C$2:$C$626,A18) -> 64
A19: Douteux | B19: Les sources décrivent un autre métier principal, malgré un nom évoquant la façade. | C19: Menuiserie, plâtrerie, étanchéité seule, entreprise générale. | D19: =COUNTIF(Base!$C$2:$C$626,A19) -> 26
A20: Hors cible (autre métier) | B20: Métier du bâtiment clairement différent. | C20: Échafaudagiste, menuisier alu, fabricant, installateur PAC. | D20: =COUNTIF(Base!$C$2:$C$626,A20) -> 9
A21: Hors cible (adjacent) | B21: Fabricant, bureau d'études, architecte : lié à la façade mais pas poseur. | C21: NAF 71.11Z, 71.12B, 22.23Z, 46.73A. | D21: =COUNTIF(Base!$C$2:$C$626,A21) -> 5
A22: Hors cible | B22: Hors du bâtiment, holding ou collectivité ; le mot-clé figurait ailleurs que dans l'activité. | C22: Restaurant, fleuriste, commune (« opération façades »). | D22: =COUNTIF(Base!$C$2:$C$626,A22) -> 23
A23: Total | D23: =SUM(D17:D22) -> 625

Sheet Limites
A1: Limites de l'étude
A2: À lire avant d'utiliser les chiffres. Chaque limite indique son effet sur les résultats.
A4: # | B4: Limite | C4: Description | D4: Effet sur les résultats | E4: Ampleur | F4: Comment la lever
A5: 1 | B5: Rappel limité au nom | C5: Seules les entreprises trouvées par la recherche de l'API sur « façade », « ravalement » ou « bardage » sont captées, en pratique surtout celles dont le nom ou l'enseigne contient ces mots. Un façadier nommé « SARL Dupont » est en général absent. | D5: Le nombre total de façadiers en France est sous-estimé. La dispersion NAF est mesurée sur cet échantillon, qui peut différer des façadiers sans mot-clé dans le nom. | E5: Non mesurable avec cette méthode. | F5: Partir de la base RGE ADEME (domaine ITE) et d'annuaires métiers, indépendamment du nom.
A6: 2 | B6: Précision du NAF peu mesurée | C6: L'étude montre que les façadiers sont dispersés sur de nombreux codes NAF. Elle ne mesure pas précisément quelle part des entreprises d'un code NAF donné sont des façadiers ; un test sur 100 entreprises en 43.99C en donne un ordre de grandeur (colonne Ampleur). | D6: Le test donne un ordre de grandeur pour le code 43.99C (environ 1 entreprise sur 4), pas une mesure précise ; les autres codes NAF ne sont pas mesurés. | E6: Test sur 100 entreprises tirées au hasard en 43.99C : 26 ont une activité façade (vraie proportion probablement entre 18 % et 35 %). | F6: Étendre le test à 43.34Z et 43.29A, et à un échantillon plus grand.
A7: 3 | B7: Vérification incomplète | C7: Une partie des entreprises n'a pu être contrôlée ni sur le web ni via le BODACC : l'outil de recherche web utilisé (Claude Code) plafonne à 200 recherches par session. | D7: Ces entreprises restent « Probable » ; le nombre de confirmés est un minimum. Elles ne sont pas réparties au hasard : la vérification a suivi l'ordre façade, ravalement, bardage, et 24 des 83 entreprises « bardage » restent non vérifiées (1 sur 392 pour « façade »). Les couvreurs-bardeurs (NAF 43.91B, 43.99A) sont donc encore sous-représentés parmi les confirmés et dans la dispersion NAF. | E7: =COUNTIF(Base!$F$2:$F$626,"non vérifié*")&" entreprises non vérifiées" -> 47 entreprises non vérifiées | F7: Poursuivre le contrôle web sur les « Probable ».
A8: 4 | B8: Nature de la preuve | C8: « Confirmé » signifie qu'une source atteste une activité façade, pas qu'elle est l'activité principale. Plusieurs annuaires recopient l'objet social ; l'activité BODACC est celle déclarée à la création ou lors d'une modification. | D8: Quelques entreprises multi-activités peuvent être surclassées. | E8: =COUNTIFS(Base!$C$2:$C$626,"Confirmé",Base!$D$2:$D$626,"Multi*")&" multi-activités identifiées" -> 10 multi-activités identifiées | F8: Entretien téléphonique ou analyse des chantiers réalisés.
A9: 5 | B9: Verdicts produits par un agent IA | C9: Les 201 verdicts web ont été rendus par un agent IA (Claude) à partir de résultats de recherche, selon les règles de l'onglet Méthodologie, sans relecture humaine systématique. | D9: Erreurs individuelles possibles, en particulier entre « Probable » et « Douteux » ; une preuve peut venir d'un résumé de recherche plutôt que de la page citée. Sur 40 verdicts vérifiés, 3 erreurs : 2 excès de prudence (un façadier classé « Douteux », un peintre classé « Probable » au lieu de « Douteux ») et 1 faux « Confirmé » (un peintre sans preuve de façade). Toutes corrigées. | E9: =COUNTIF(Base!$F$2:$F$626,"recherche web*")&" verdicts rendus par l'agent IA, chacun avec sa source" -> 201 verdicts rendus par l'agent IA, chacun avec sa source | F9: Fait le 26/09/2026 sur 40 verdicts tirés au hasard : 20 relus par un humain (18 justes) et 20 contre-vérifiés sur sources primaires (19 justes), soit 37 sur 40 (93 %).
A10: 6 | B10: Effectifs | C10: Les effectifs sont des tranches INSEE publiées avec un décalage d'un à deux ans. Certains annuaires affichent des effectifs plus faibles. | D10: Quelques entreprises peuvent être aujourd'hui sous 6 salariés. | E10: Ponctuel | F10: Contrôler l'effectif au moment de la prospection.
A11: 7 | B11: Définition du façadier | C11: Les couvreurs-étancheurs faisant du bardage et les poseurs de façade légère sont inclus dans les confirmés, mais segmentés. La colonne Spécialité est attribuée automatiquement (nom, NAF, mots de la preuve) : un couvreur dont le nom contient « façade » peut être rangé en cœur de métier. | D11: Le total dépend de la définition retenue ; la répartition par spécialité est indicative (la part « cœur de métier » est un maximum). | E11: =(COUNTIFS(Base!$C$2:$C$626,"Confirmé",Base!$D$2:$D$626,"Couvreur*")+COUNTIFS(Base!$C$2:$C$626,"Confirmé",Base!$D$2:$D$626,"Façade légère*"))&" entreprises concernées" -> 50 entreprises concernées | F11: Filtrer la colonne Spécialité selon la définition souhaitée.
A12: 8 | B12: Données datées | C12: Statuts juridiques et procédures collectives relevés au 24/09/2026. Alertes anciennes et plans en cours revérifiés manuellement le 26/09/2026. | D12: La situation évolue vite pour les entreprises en procédure. | E12: — | F12: Revérifier le BODACC avant toute campagne.
A13: 9 | B13: Mots-clés secondaires non utilisés | C13: « Vêtage », « vêture », « enduit » et « isolation thermique extérieure » n'ont pas été recherchés. Exemple : SOGEP (Société Générale d'Enduits Parisiens), façadier trouvé lors du test de précision NAF, est absent de l'étude. | D13: Quelques spécialistes de l'enveloppe sont absents. | E13: — | F13: Relancer l'extraction avec ces mots-clés.

Sheet Recommandations
A1: Recommandations et prochaines étapes
A3: Priorité | B3: Action | C3: Pourquoi | D3: Effort
A4: 1 | B4: Prospecter l'onglet Prospects en priorité : les entreprises en procédure collective en sont déjà écartées. | C4: Liste vérifiée, sans alerte juridique. | D4: Immédiat
A5: 2 | B5: Ne pas utiliser le code NAF comme critère de ciblage principal ; s'appuyer sur la qualification RGE ITE et l'activité déclarée. | C5: Aucun code ne suffit seul : il en faut 8 pour couvrir 90 % des façadiers, et ces codes sont partagés avec d'autres métiers. | D5: Faible
A6: 3 | B6: Terminer la vérification des entreprises « Probable » (contrôle web). | C6: Porte le nombre de confirmés à sa valeur réelle. | D6: Faible : relancer une session avec un quota de recherches plus élevé (environ 2 h 30 à la main)
A7: 4 | B7: Élargir le rappel : extraire toutes les entreprises RGE « isolation des murs par l'extérieur » de 6 à 199 salariés, quel que soit leur nom. | C7: Capte les façadiers sans mot-clé dans le nom. | D7: Moyen
A8: 5 | B8: Mesurer la précision du NAF sur un échantillon aléatoire de 43.99C, 43.34Z et 43.29A. Premier test réalisé sur 100 entreprises en 43.99C (onglet Test précision NAF) ; à étendre à 43.34Z et 43.29A. | C8: Chiffre le coût d'un ciblage par NAF (faux positifs). | D8: Moyen
A9: 6 | B9: Revérifier le BODACC juste avant chaque campagne. | C9: Les procédures collectives évoluent vite. | D9: Faible

Sheet Prospects
A1: Prospects : façadiers confirmés sans alerte juridique
A2: Filtrer la colonne Spécialité pour appliquer la définition souhaitée.
A4: SIREN | B4: Nom | C4: Classement | D4: Spécialité | E4: Alerte | F4: Code NAF | G4: Libellé NAF | H4: Effectif (salariés) | I4: Commune | J4: Code postal | K4: Département | L4: Méthode de vérification | M4: Preuve | N4: Source
A5: 851694190 | B5: CAVIEUX FACADES | C5: Confirmé | D5: Façadier (ravalement, enduits, ITE, bardage) | F5: 43.99C | G5: Travaux de maçonnerie générale et gros œuvre de bâtiment | H5: 6 à 9 | I5: SAINT-ANDRE-DE-CORCY | J5: 01390 | K5: 01 | L5: automatique (RGE ADEME / site web) | M5: RGE isolation des murs par l'extérieur (ADEME) ; site web : enduit, facade, ite, ravalement ; mot-clé dans le nom/enseigne ; NAF 43.99C BTP cohérent | N5: https://data.ademe.fr/datasets/liste-des-entreprises-rge-2
A6: 419678396 | B6: E.R.T.B.I. (ERTBI FACADES ENVIRONNEMENT) | C6: Confirmé | D6: Multi-activité (façade parmi d'autres métiers) | F6: 43.99B | G6: Travaux de montage de structures métalliques | H6: 6 à 9 | I6: CHARNOZ-SUR-AIN | J6: 01800 | K6: 01 | L6: recherche web (agent IA) | M6: échafaudage + travaux de façade extérieure, plâtrerie (multi-activité) | N6: https://lyon-entreprises.com/Annuaire/ERTBI-FACADES-ENVIRONNEMENT-20427/coordonnees-caluire-et-cuire.html
A7: 538058041 | B7: REIS BARDAGE | C7: Confirmé | D7: Couvreur / étancheur faisant du bardage | F7: 43.91B | G7: Travaux de couverture par éléments | H7: 6 à 9 | I7: LA BOISSE | J7: 01120 | K7: 01 | L7: BODACC (activité déclarée au greffe) | M7: activité déclarée : Travaux de couverture et de bardage. | N7: https://www.bodacc.fr/ (SIREN 538058041)
A8: 915208334 | B8: TECHNO BARDAGE | C8: Confirmé | D8: Couvreur / étancheur faisant du bardage | F8: 43.91B | G8: Travaux de couverture par éléments | H8: 6 à 9 | I8: MONTLUEL | J8: 01120 | K8: 01 | L8: BODACC (activité déclarée au greffe) | M8: activité déclarée : couverture et bardage | N8: https://www.bodacc.fr/ (SIREN 915208334)
A9: 828285437 | B9: CFP TECHNI-FACADES | C9: Confirmé | D9: Façadier (ravalement, enduits, ITE, bardage) | F9: 43.99C | G9: Travaux de maçonnerie générale et gros œuvre de bâtiment | H9: 6 à 9 | I9: BRUGHEAS | J9: 03700 | K9: 03 | L9: automatique (RGE ADEME / site web) | M9: RGE isolation des murs par l'extérieur (ADEME) ; mot-clé dans le nom/enseigne ; NAF 43.99C BTP cohérent | N9: https://data.ademe.fr/datasets/liste-des-entreprises-rge-2
A10: 978246767 | B10: DK FACADE ITE PEINTURE | C10: Confirmé | D10: Façadier (ravalement, enduits, ITE, bardage) | F10: 43.99C | G10: Travaux de maçonnerie générale et gros œuvre de bâtiment | H10: 6 à 9 | I10: MANOSQUE | J10: 04100 | K10: 04 | L10: recherche web (agent IA) | M10: ravalement, ITE, peinture | N10: https://servicesartisans.fr/services/facadier/manosque/dk-facade-ite-peinture-978246767
A11: 814514162 | B11: K 2 (CONCEPT FACADES) | C11: Confirmé | D11: Façadier (ravalement, enduits, ITE, bardage) | F11: 43.99C | G11: Travaux de maçonnerie générale et gros œuvre de bâtiment | H11: 20 à 49 | I11: BIOT | J11: 06410 | K11: 06 | L11: recherche web (agent IA) | M11: enseigne CONCEPT FACADES : ravalement, peinture, ITE ; 20-49 salariés | N11: https://annuaire-entreprises.data.gouv.fr/entreprise/814514162
A12: 847633633 | B12: SASU BATI PROJECT FACADES | C12: Confirmé | D12: Façadier (ravalement, enduits, ITE, bardage) | F12: 43.33Z | G12: Travaux de revêtement des sols et des murs | H12: 6 à 9 | I12: ANTIBES | J12: 06600 | K12: 06 | L12: recherche web (agent IA) | M12: ravalement / nettoyage de façades (+ négoce carrelage) | N12: https://www.pagesjaunes.fr/pros/60786535
A13: 837629419 | B13: SILLA FACADES | C13: Confirmé | D13: Façadier (ravalement, enduits, ITE, bardage) | F13: 43.99C | G13: Travaux de maçonnerie générale et gros œuvre de bâtiment | H13: 20 à 49 | I13: CAGNES-SUR-MER | J13: 06800 | K13: 06 | L13: recherche web (agent IA) | M13: travaux de façade : nettoyage, isolation thermique | N13: https://www.pagesjaunes.fr/pros/55671292
A14: 819985979 | B14: FACADES A.Z. | C14: Confirmé | D14: Façadier (ravalement, enduits, ITE, bardage) | F14: 43.99C | G14: Travaux de maçonnerie générale et gros œuvre de bâtiment | H14: 10 à 19 | I14: SAINT-DIDIER-SOUS-AUBENAS | J14: 07200 | K14: 07 | L14: automatique (RGE ADEME / site web) | M14: RGE isolation des murs par l'extérieur (ADEME) ; mot-clé dans le nom/enseigne ; NAF 43.99C BTP cohérent | N14: https://data.ademe.fr/datasets/liste-des-entreprises-rge-2
A15: 433256237 | B15: FACADES ARDECHOISES | C15: Confirmé | D15: Façadier (ravalement, enduits, ITE, bardage) | F15: 43.99A | G15: Travaux d'étanchéification | H15: 20 à 49 | I15: ANNONAY | J15: 07100 | K15: 07 | L15: automatique (RGE ADEME / site web) | M15: RGE isolation des murs par l'extérieur (ADEME) ; site web : enduit, ravalement ; mot-clé dans le nom/enseigne ; NAF 43.99A BTP cohérent | N15: https://data.ademe.fr/datasets/liste-des-entreprises-rge-2
A16: 798080495 | B16: SUD ARDECHE FACADES | C16: Confirmé | D16: Façadier (ravalement, enduits, ITE, bardage) | F16: 43.99C | G16: Travaux de maçonnerie générale et gros œuvre de bâtiment | H16: 6 à 9 | I16: AUBENAS | J16: 07200 | K16: 07 | L16: automatique (RGE ADEME / site web) | M16: RGE isolation des murs par l'extérieur (ADEME) ; mot-clé dans le nom/enseigne ; NAF 43.99C BTP cohérent | N16: https://data.ademe.fr/datasets/liste-des-entreprises-rge-2
... A469: 330940172 | B469: SOC KOUROU BARDAGE (SKB) | C469: Confirmé | D469: Couvreur / étancheur faisant du bardage | F469: 43.91B | G469: Travaux de couverture par éléments | H469: 6 à 9 | I469: KOUROU | J469: 97310 | K469: 973 | L469: BODACC (activité déclarée au greffe) | M469: activité déclarée : non précisée / bardage, entretien, couverture, étanchéité et tout ce qui touche à l'industrie des travaux publics | N469: https://www.bodacc.fr/ (SIREN 330940172)

Sheet À vérifier et exclus
A1: Entreprises à vérifier, douteuses, hors cible ou sous alerte
A2: Probables et douteux à vérifier ; hors cible avec motif ; confirmés en procédure collective.
A4: SIREN | B4: Nom | C4: Classement | D4: Spécialité | E4: Alerte | F4: Code NAF | G4: Libellé NAF | H4: Effectif (salariés) | I4: Commune | J4: Code postal | K4: Département | L4: Méthode de vérification | M4: Preuve | N4: Source
A5: 814774246 | B5: SOLUTIONS POSES FACADES (SPF) (SPF) | C5: Douteux | F5: 43.32B | G5: Travaux de menuiserie métallique et serrurerie | H5: 6 à 9 | I5: ETAMPES-SUR-MARNE | J5: 02400 | K5: 02 | L5: recherche web (agent IA) | M5: activité décrite = menuiserie métallique / serrurerie ; façade non attestée | N5: https://www.pappers.fr/entreprise/spf-solutions-poses-facades-814774246
A6: 885361626 | B6: D.A.F. COUVERTURE BARDAGE | C6: Probable | F6: 43.91B | G6: Travaux de couverture par éléments | H6: 10 à 19 | I6: VICHY | J6: 03200 | K6: 03 | L6: non vérifié (quota de 200 recherches web atteint) | M6: mot-clé dans le nom/enseigne ; NAF 43.91B BTP cohérent
A7: 210400453 | B7: COMMUNE DE CERESTE-EN-LUBERON | C7: Hors cible | F7: 84.11Z | G7: Administration publique générale | H7: 20 à 49 | I7: CERESTE-EN-LUBERON | J7: 04280 | K7: 04 | L7: recherche web (agent IA) | M7: collectivité (commune) — enseigne « opération façade » | N7: https://annuaire-entreprises.data.gouv.fr/entreprise/210400453
A8: 351963350 | B8: SOCIETE DE RAVALEMENT D'ISOLATION ET D'ETANCHEITE (SORIE) | C8: Confirmé | D8: Façadier (ravalement, enduits, ITE, bardage) | E8: Vigilance : redressement judiciaire en cours | F8: 43.34Z | G8: Travaux de peinture et vitrerie | H8: 10 à 19 | I8: LA ROQUETTE-SUR-SIAGNE | J8: 06550 | K8: 06 | L8: BODACC (activité déclarée au greffe) | M8: activité déclarée : entreprise d'étanchéité en bâtiment de ravalement de bâtiments. / Entreprise d'étanchéité en bâtiment de ravalement de bâtiments | N8: https://www.bodacc.fr/ (SIREN 351963350)
A9: 786020206 | B9: ETABLISSEMENTS WARSMANN | C9: Hors cible (autre métier) | F9: 43.32B | G9: Travaux de menuiserie métallique et serrurerie | H9: 20 à 49 | I9: NOUZONVILLE | J9: 08700 | K9: 08 | L9: recherche web (agent IA) | M9: menuiserie aluminium et serrurerie, structures métalliques ; façade non attestée | N9: https://www.warsmann.fr/
A10: 828250373 | B10: OCCITANIE BATIMENT FACADE | C10: Probable | F10: 43.99C | G10: Travaux de maçonnerie générale et gros œuvre de bâtiment | H10: 10 à 19 | I10: MONTREDON-DES-CORBIERES | J10: 11100 | K10: 11 | L10: recherche web (agent IA) | M10: sources = annuaires uniquement ; NAF maçonnerie | N10: https://www.pappers.fr/entreprise/occitanie-batiment-facade-828250373
A11: 887981249 | B11: SEBAPROMOTION | C11: Hors cible | F11: 70.22Z | G11: Conseil pour les affaires et autres conseils de gestion | H11: 10 à 19 | I11: SEBAZAC-CONCOURES | J11: 12740 | K11: 12 | L11: automatique (NAF hors BTP) + BODACC | M11: NAF 70.22Z hors BTP ; activité déclarée : toutes prestations de services en matière commerciale et de gestion, distribution et commercialisation de produits, objets, marchandises pour le compte de tous tiers | N11: https://www.bodacc.fr/ (SIREN 887981249)
A12: 902657063 | B12: AYDIN FACADES | C12: Probable | F12: 43.99C | G12: Travaux de maçonnerie générale et gros œuvre de bâtiment | H12: 10 à 19 | I12: PEYPIN | J12: 13124 | K12: 13 | L12: recherche web (agent IA) | M12: activité décrite = maçonnerie de rénovation ; façade non explicite | N12: https://peypin.localbiz.fr/fiche-aydin-facades-13073-90265706300019
A13: 825010796 | B13: CHAPES CARRELAGES BRISENO (POSE DE PIERRES ET DE TOUT TYPE DE REVETEMENT DE SOLS MURS ET FACADES) | C13: Hors cible (autre métier) | F13: 43.33Z | G13: Travaux de revêtement des sols et des murs | H13: 6 à 9 | I13: BOULBON | J13: 13150 | K13: 13 | L13: recherche web (agent IA) | M13: chapes, carrelage, pose de pierres ; pas façadier | N13: https://www.pappers.fr/entreprise/chapes-carrelages-briseno-825010796
A14: 815129960 | B14: CHARPENTE COUVERTURE BARDAGE (CCB) | C14: Probable | F14: 43.99B | G14: Travaux de montage de structures métalliques | H14: 10 à 19 | I14: BERRE-L'ETANG | J14: 13130 | K14: 13 | L14: non vérifié (quota de 200 recherches web atteint) | M14: mot-clé dans le nom/enseigne ; NAF 43.99B BTP cohérent
A15: 527988257 | B15: LAVARENNE | C15: Hors cible | F15: 10.71C | G15: Boulangerie et boulangerie-pâtisserie | H15: 20 à 49 | I15: VENELLES | J15: 13770 | K15: 13 | L15: automatique (NAF hors BTP) | M15: NAF 10.71C hors BTP
A16: 894901479 | B16: RIP 13 RAVALEMENT ISOLATION PEINTURE 13 | C16: Probable | F16: 43.33Z | G16: Travaux de revêtement des sols et des murs | H16: 6 à 9 | I16: MARSEILLE | J16: 13014 | K16: 13 | L16: non vérifié (quota de 200 recherches web atteint) | M16: mot-clé dans le nom/enseigne ; NAF 43.33Z BTP cohérent
A17: 520980517 | B17: ATLANTIQUE BARDAGE | C17: Douteux | F17: 43.29A | G17: Travaux d'isolation | H17: 6 à 9 | I17: PERIGNY | J17: 17180 | K17: 17 | L17: BODACC (activité déclarée au greffe) | M17: activité déclarée sans mention façade : Travaux d'amélioration thermique, amélioration de l'habitat, négoce de matériaux d'isolation | N17: https://www.bodacc.fr/ (SIREN 520980517)
A18: 481411882 | B18: CITYA COTE DE BEAUTE (CITYA COTE DE BEAUTE) | C18: Hors cible | F18: 68.32A | G18: Administration d'immeubles et autres biens immobiliers | H18: 10 à 19 | I18: ROYAN | J18: 17200 | K18: 17 | L18: automatique (NAF hors BTP) + BODACC | M18: NAF 68.32A hors BTP ; activité déclarée : transaction immobilière, gestion immobilière et syndic de copropriété / agence immobilière, transaction sur appartement et maison, gestion et location | N18: https://www.bodacc.fr/ (SIREN 481411882)
A19: 534295613 | B19: JBC FACADES | C19: Douteux | E19: NE PAS PROSPECTER : liquidation judiciaire | F19: 43.31Z | G19: Travaux de plâtrerie | H19: 6 à 9 | I19: ARS-EN-RE | J19: 17590 | K19: 17 | L19: recherche web (agent IA) | M19: activité déclarée plâtrerie ; aucune trace d'activité façade | N19: https://www.mon-platrier.fr/entreprise/jbc-facades-534295613/
A20: 500592092 | B20: MG+ARCHITECTES | C20: Hors cible (adjacent) | F20: 71.11Z | G20: Activités d'architecture | H20: 6 à 9 | I20: SAINTES | J20: 17100 | K20: 17 | L20: BODACC (activité déclarée au greffe) | M20: activité déclarée : profession d'architecte, urbaniste et paysagiste | N20: https://www.bodacc.fr/ (SIREN 500592092)
A21: 409596244 | B21: NOUVELLE AQUITAINE RAVALEMENT (NAR) | C21: Confirmé | D21: Façadier (ravalement, enduits, ITE, bardage) | E21: Radiée au BODACC | F21: 43.34Z | G21: Travaux de peinture et vitrerie | H21: 10 à 19 | I21: ROYAN | J21: 17200 | K21: 17 | L21: automatique (RGE ADEME / site web) | M21: RGE isolation des murs par l'extérieur (ADEME) ; mot-clé dans le nom/enseigne ; NAF 43.34Z BTP cohérent | N21: https://data.ademe.fr/datasets/liste-des-entreprises-rge-2
A22: 445343718 | B22: RAVALEMENT DE FRANCE 17 (R.D.F. 17) | C22: Douteux | F22: 43.33Z | G22: Travaux de revêtement des sols et des murs | H22: 10 à 19 | I22: SAINT-MEDARD-D'AUNIS | J22: 17220 | K22: 17 | L22: BODACC (activité déclarée au greffe) | M22: activité déclarée sans mention façade : activité de zinguerie, gouttière aluminium, couverture de bâtiments, pose de cloisons sèches, tous travaux de fabrication, pose et réparation dans lesdits domaines. | N22: https://www.bodacc.fr/ (SIREN 445343718)
A23: 844247460 | B23: RAVALEMENT DE FRANCE 44 (R.D.F. 44) | C23: Confirmé | D23: Façadier (ravalement, enduits, ITE, bardage) | E23: NE PAS PROSPECTER : liquidation judiciaire | F23: 43.39Z | G23: Autres travaux de finition | H23: 10 à 19 | I23: SAINT-MEDARD-D'AUNIS | J23: 17220 | K23: 17 | L23: BODACC (activité déclarée au greffe) | M23: activité déclarée : réalisation d'enduit de façades de sablage de façades nettoyage de façades peinture en bâtiment | N23: https://www.bodacc.fr/ (SIREN 844247460)
A24: 499253219 | B24: ARCOFA - ARCHITECTURES CONSTRUCTION FACADES | C24: Hors cible | F24: 64.20Z | G24: Activités des sociétés holding | H24: 20 à 49 | I24: OUGES | J24: 21600 | K24: 21 | L24: recherche web (agent IA) | M24: holding (NAF 64.20Z) ; pas d'activité opérationnelle propre | N24: https://www.pappers.fr/entreprise/arcofa-architectures-construction-facades-499253219
A25: 879989101 | B25: QECB (QECB-ETANCHEITE-COUVERTURE-BARDAGE) | C25: Probable | F25: 43.91B | G25: Travaux de couverture par éléments | H25: 6 à 9 | I25: QUESSOY | J25: 22120 | K25: 22 | L25: non vérifié (quota de 200 recherches web atteint) | M25: mot-clé dans le nom/enseigne ; NAF 43.91B BTP cohérent
A26: 492274543 | B26: MF HABILLEZ VOS FACADES | C26: Confirmé | D26: Façadier (ravalement, enduits, ITE, bardage) | E26: NE PAS PROSPECTER : plan de cession | F26: 43.99C | G26: Travaux de maçonnerie générale et gros œuvre de bâtiment | H26: 20 à 49 | I26: MALATAVERNE | J26: 26780 | K26: 26 | L26: recherche web (agent IA) | M26: ravalement, enduits, bardage (devenu Indigo MF, Indigo Groupe) | N26: https://www.indigogroupe.fr/details-indigo+mf-765
A27: 309124477 | B27: POMPES FUNEBRES ET MARBRERIE BERTHELOT (POMPES FUNEBRES ET MARBRERIE BERTHELOT) | C27: Hors cible | F27: 96.03Z | G27: Services funéraires | H27: 100 à 199 | I27: GISORS | J27: 27140 | K27: 27 | L27: automatique (NAF hors BTP) + BODACC | M27: NAF 96.03Z hors BTP ; activité déclarée : Pompes funèbres, marbrerie, vente au détail de fleurs artificielles et naturelles et ornements funéraires. / Pompes funèbres, marbrerie, vente au détail de fleurs Artificilelles et naturelles et ornements funéraires. / pompes funèbres marbrerie vente au détails de fleur artificielles et naturelles et ornement funéraires. / pompes funèbres marbrerie vente au détail de fleur artificielles et naturel | N27: https://www.bodacc.fr/ (SIREN 309124477)
A28: 832085773 | B28: N'CO (LORENOVE, NCO FACADE) | C28: Hors cible (autre métier) | F28: 46.13Z | G28: Intermédiaires du commerce en bois et matériaux de construction | H28: 6 à 9 | I28: VERNOUILLET | J28: 28500 | K28: 28 | L28: recherche web (agent IA) | M28: franchise Lorenove : négoce/pose de menuiseries (fenêtres) | N28: https://www.fenetres-lorenove.fr/actualite-offres/nco-lorenove-votre-expert-en-menuiseries-a-dreux
A29: 509730743 | B29: SERVICE ASSISTANCE BARDAGE ETANCHEITE (SABE) | C29: Confirmé | D29: Couvreur / étancheur faisant du bardage | E29: NE PAS PROSPECTER : liquidation judiciaire | F29: 43.99A | G29: Travaux d'étanchéification | H29: 6 à 9 | I29: LES VILLAGES VOVEENS | J29: 28150 | K29: 28 | L29: BODACC (activité déclarée au greffe) | M29: activité déclarée : Bardage étanchéité | N29: https://www.bodacc.fr/ (SIREN 509730743)
A30: 840902183 | B30: JOAQUIM SOUSA ANDRADE (JA CHARPENTE BARDAGE) | C30: Probable | F30: 43.91A | G30: Travaux de charpente | H30: 6 à 9 | I30: BASTIA | J30: 20200 | K30: 2B | L30: non vérifié (quota de 200 recherches web atteint) | M30: mot-clé dans le nom/enseigne ; NAF 43.91A BTP cohérent
A31: 492849252 | B31: M.G.P. CONSTRUCTION - RENOVATION - FACADES | C31: Douteux | F31: 43.99C | G31: Travaux de maçonnerie générale et gros œuvre de bâtiment | H31: 10 à 19 | I31: SAINT-COME-ET-MARUEJOLS | J31: 30870 | K31: 30 | L31: recherche web (agent IA) | M31: activité décrite = isolation intérieure + couverture/charpente | N31: https://www.pappers.fr/entreprise/mgp-construction-renovation-facades-492849252
A32: 533835260 | B32: SAINT GENIES BATIMENT FACADES - SGBF (SGBF) | C32: Confirmé | D32: Façadier (ravalement, enduits, ITE, bardage) | E32: Vigilance : sauvegarde en cours | F32: 43.99C | G32: Travaux de maçonnerie générale et gros œuvre de bâtiment | H32: 10 à 19 | I32: SAINT-GENIES-DE-MALGOIRES | J32: 30190 | K32: 30 | L32: recherche web (agent IA) | M32: réhabilitation de façades, ITE | N32: https://www.pagesjaunes.fr/pros/55608996
A33: 833611585 | B33: BRL FACADES | C33: Confirmé | D33: Façadier (ravalement, enduits, ITE, bardage) | E33: Vigilance : redressement judiciaire en cours | F33: 43.99C | G33: Travaux de maçonnerie générale et gros œuvre de bâtiment | H33: 10 à 19 | I33: TOULOUSE | J33: 31100 | K33: 31 | L33: recherche web (agent IA) | M33: façadier (enduits, rénovation façade, ITE) ; EN REDRESSEMENT JUDICIAIRE | N33: https://www.brl-facades-toulouse.fr/
A34: 397941162 | B34: ENTREPRISE DE TRAVAUX ET DE RAVALEMENT (ETR) | C34: Probable | F34: 43.39Z | G34: Autres travaux de finition | H34: 6 à 9 | I34: PLAISANCE-DU-TOUCH | J34: 31830 | K34: 31 | L34: non vérifié (quota de 200 recherches web atteint) | M34: mot-clé dans le nom/enseigne ; NAF 43.39Z BTP cohérent
A35: 534958327 | B35: NATUREL FACADES (NATUREL FACADES) | C35: Confirmé | D35: Façadier (ravalement, enduits, ITE, bardage) | E35: Vigilance : redressement judiciaire en cours | F35: 43.31Z | G35: Travaux de plâtrerie | H35: 6 à 9 | I35: SEYSSES | J35: 31600 | K35: 31 | L35: recherche web (agent IA) | M35: enduits décoratifs de façade + ITE (neuf/rénovation) | N35: https://juniorfacades.fr/
A36: 810036244 | B36: SARL SPR (SOL PEINTURE RAVALEMENT) | C36: Douteux | F36: 43.31Z | G36: Travaux de plâtrerie | H36: 6 à 9 | I36: TOULOUSE | J36: 31200 | K36: 31 | L36: BODACC (activité déclarée au greffe) | M36: activité déclarée sans mention façade : pose de plaques de plâtre, peinture, carrelage, revêtement de sol, maçonnerie générale de second oeuvre / Maçonnerie générale. | N36: https://www.bodacc.fr/ (SIREN 810036244)
A37: 517550679 | B37: ICNERGIE (AQUITAINE BARDAGE COUVERTURE&QUOT;) | C37: Hors cible | F37: 70.22Z | G37: Conseil pour les affaires et autres conseils de gestion | H37: 6 à 9 | I37: LORMONT | J37: 33310 | K37: 33 | L37: automatique (NAF hors BTP) + BODACC | M37: mot-clé dans le nom/enseigne ; NAF 70.22Z hors BTP ; activité déclarée : conseil et distribution de produits d'économie d'énergie. | N37: https://www.bodacc.fr/ (SIREN 517550679)
A38: 472202845 | B38: SOC RENOVATION ENTRETIEN FACADES BETON | C38: Confirmé | D38: Façadier (ravalement, enduits, ITE, bardage) | E38: NE PAS PROSPECTER : plan de cession | F38: 43.29A | G38: Travaux d'isolation | H38: 50 à 99 | I38: LORMONT | J38: 33310 | K38: 33 | L38: recherche web (agent IA) | M38: SOREFAB : rénovation/étanchéité de façades béton, 50-99 salariés | N38: https://www.prodestravaux.com/entreprise/47220284500112
A39: 952917441 | B39: ABD FACADE | C39: Probable | F39: 43.34Z | G39: Travaux de peinture et vitrerie | H39: 10 à 19 | I39: CLERMONT-L'HERAULT | J39: 34800 | K39: 34 | L39: recherche web (contre-vérification) | M39: peintre (peinture intérieure et extérieure, enduits décoratifs) ; aucune source ne décrit de travaux de façade : reclassé « Probable » lors de la contre-vérification (26/09/2026) | N39: https://guide-de-l-habitat.fr/artisans/clermont-l-herault/peintre/abd-facade/
A40: 837604297 | B40: ALS FACADES (ALS FACADES) | C40: Probable | F40: 43.34Z | G40: Travaux de peinture et vitrerie | H40: 6 à 9 | I40: MARAUSSAN | J40: 34370 | K40: 34 | L40: non vérifié (quota de 200 recherches web atteint) | M40: mot-clé dans le nom/enseigne ; NAF 43.34Z BTP cohérent
A41: 910405794 | B41: AMI FACADE | C41: Probable | F41: 43.99C | G41: Travaux de maçonnerie générale et gros œuvre de bâtiment | H41: 6 à 9 | I41: MONTPELLIER | J41: 34080 | K41: 34 | L41: recherche web (agent IA) | M41: sources = annuaires uniquement (créée 2022) | N41: https://www.societe.com/societe/ami-facade-910405794.html
A42: 502360167 | B42: LATIF ATAS (VIZION FACADE) | C42: Douteux | F42: 43.99D | G42: Autres travaux spécialisés de construction | H42: 6 à 9 | I42: BEZIERS | J42: 34500 | K42: 34 | L42: recherche web (agent IA) | M42: entrepreneur individuel, revêtements sols/murs ; enseigne VIZION FACADE fermée en 2009 | N42: https://www.pappers.fr/entreprise/atas-latif-502360167
A43: 840973366 | B43: LES FACADES VERTES (LES FACADES VERTES) | C43: Confirmé | D43: Façadier (ravalement, enduits, ITE, bardage) | E43: NE PAS PROSPECTER : liquidation judiciaire | F43: 43.99C | G43: Travaux de maçonnerie générale et gros œuvre de bâtiment | H43: 6 à 9 | I43: BEZIERS | J43: 34500 | K43: 34 | L43: recherche web (agent IA) | M43: travaux de façade, rénovation d'enveloppe, ITE | N43: https://lesfacadesvertes.fr/
A44: 432366425 | B44: ENTREPRISE SIMOES RAVALEMENT | C44: Probable | F44: 43.34Z | G44: Travaux de peinture et vitrerie | H44: 6 à 9 | I44: VERN-SUR-SEICHE | J44: 35770 | K44: 35 | L44: non vérifié (quota de 200 recherches web atteint) | M44: mot-clé dans le nom/enseigne ; NAF 43.34Z BTP cohérent
A45: 841061104 | B45: NEWBAKERY DEVELOPPEMENT | C45: Hors cible | F45: 56.10C | G45: Restauration de type rapide | H45: 20 à 49 | I45: CHATEAUGIRON | J45: 35410 | K45: 35 | L45: automatique (NAF hors BTP) + BODACC | M45: NAF 56.10C hors BTP ; activité déclarée : Fonds de commerce de fabrication et vente de produits de boulangerie, de pâtisserie, de viennoiserie, de traiteur sucré salé, de petite restauration sur place et ou à emporter de confiserie, de boissons chaudes et froides / salon de restauration rapide, snacking, salon de thé, l'achat et la vente de produits alimentaires, d'épicerie fine et de boissons. / Boulangerie-pâtisserie / salon de restaura | N45: https://www.bodacc.fr/ (SIREN 841061104)
A46: 421775016 | B46: SARL OP RAVALEMENT | C46: Probable | F46: 43.34Z | G46: Travaux de peinture et vitrerie | H46: 10 à 19 | I46: LA BOUEXIERE | J46: 35340 | K46: 35 | L46: non vérifié (quota de 200 recherches web atteint) | M46: mot-clé dans le nom/enseigne ; NAF 43.34Z BTP cohérent
A47: 243600293 | B47: CC LEVROUX BOISCHAUT CHAMPAGNE | C47: Hors cible | F47: 84.11Z | G47: Administration publique générale | H47: 20 à 49 | I47: LEVROUX | J47: 36110 | K47: 36 | L47: recherche web (agent IA) | M47: collectivité (communauté de communes) — enseigne « opération façades » | N47: https://annuaire-entreprises.data.gouv.fr/entreprise/243600293
A48: 453896920 | B48: EURO BARDAGE | C48: Probable | F48: 43.99B | G48: Travaux de montage de structures métalliques | H48: 6 à 9 | I48: MONNAIE | J48: 37380 | K48: 37 | L48: non vérifié (quota de 200 recherches web atteint) | M48: mot-clé dans le nom/enseigne ; NAF 43.99B BTP cohérent
A49: 511537169 | B49: PRO BARDAGE | C49: Probable | F49: 43.99A | G49: Travaux d'étanchéification | H49: 6 à 9 | I49: CUSSAY | J49: 37240 | K49: 37 | L49: non vérifié (quota de 200 recherches web atteint) | M49: mot-clé dans le nom/enseigne ; NAF 43.99A BTP cohérent
A50: 810103317 | B50: BMC BARDAGE | C50: Confirmé | D50: Couvreur / étancheur faisant du bardage | E50: NE PAS PROSPECTER : liquidation judiciaire | F50: 43.99A | G50: Travaux d'étanchéification | H50: 10 à 19 | I50: VIENNE | J50: 38200 | K50: 38 | L50: BODACC (activité déclarée au greffe) | M50: activité déclarée : activité en direct ou en sous-traitance, d'étanchéité, bardage | N50: https://www.bodacc.fr/ (SIREN 810103317)
A51: 814092300 | B51: IDEAL SYSTEMES (IDEAL SYSTEME) | C51: Hors cible (autre métier) | F51: 43.99C | G51: Travaux de maçonnerie générale et gros œuvre de bâtiment | H51: 6 à 9 | I51: ESTRABLIN | J51: 38780 | K51: 38 | L51: recherche web (agent IA) | M51: installateur pompes à chaleur / VMC ; pas façadier | N51: https://ideal-systeme.fr/
A52: 484147905 | B52: MP BARDAGE | C52: Probable | F52: 43.99A | G52: Travaux d'étanchéification | H52: 6 à 9 | I52: CRISSEY | J52: 39100 | K52: 39 | L52: non vérifié (quota de 200 recherches web atteint) | M52: mot-clé dans le nom/enseigne ; NAF 43.99A BTP cohérent
A53: 842901589 | B53: DA SILVA RAVALEMENT | C53: Confirmé | D53: Façadier (ravalement, enduits, ITE, bardage) | E53: NE PAS PROSPECTER : liquidation judiciaire | F53: 43.99C | G53: Travaux de maçonnerie générale et gros œuvre de bâtiment | H53: 6 à 9 | I53: BLOIS | J53: 41000 | K53: 41 | L53: recherche web (agent IA) | M53: ravalement, peinture, ITE, imperméabilisation | N53: https://www.pagesjaunes.fr/pros/57651911
A54: 905203204 | B54: GOLD RAVALEMENT | C54: Douteux | F54: 43.99C | G54: Travaux de maçonnerie générale et gros œuvre de bâtiment | H54: 6 à 9 | I54: ROMORANTIN-LANTHENAY | J54: 41200 | K54: 41 | L54: recherche web (agent IA) | M54: activité décrite = gros œuvre béton (1-2 salariés selon annuaire) ; façade non attestée | N54: https://omizi.com/professionnels/macons/loir-et-cher/romorantin-lanthenay
A55: 894400332 | B55: COUVERTURE METALLERIE BARDAGE (COUVERTURE METALLERIE BARDAGE) | C55: Probable | F55: 43.29A | G55: Travaux d'isolation | H55: 10 à 19 | I55: ROANNE | J55: 42300 | K55: 42 | L55: non vérifié (quota de 200 recherches web atteint) | M55: mot-clé dans le nom/enseigne ; NAF 43.29A BTP cohérent
A56: 909138596 | B56: RSR ETANCHEITE BARDAGE | C56: Probable | F56: 43.99A | G56: Travaux d'étanchéification | H56: 6 à 9 | I56: LA FOUILLOUSE | J56: 42480 | K56: 42 | L56: non vérifié (quota de 200 recherches web atteint) | M56: mot-clé dans le nom/enseigne ; NAF 43.99A BTP cohérent
A57: 409695566 | B57: ARTISANS REUNIS BOIS ATLANTIQUE (ARBA) | C57: Hors cible (adjacent) | F57: 46.73A | G57: Commerce de gros (commerce interentreprises) de bois et de matériaux de construction | H57: 100 à 199 | I57: SAINTE-LUCE-SUR-LOIRE | J57: 44980 | K57: 44 | L57: BODACC (activité déclarée au greffe) | M57: activité déclarée : groupement d'achat au service des artisans associés (négoce de matériaux) | N57: https://www.bodacc.fr/ (SIREN 409695566)
A58: 510390230 | B58: ATLANTHERM FACADES | C58: Confirmé | D58: Façadier (ravalement, enduits, ITE, bardage) | E58: NE PAS PROSPECTER : liquidation judiciaire | F58: 43.99C | G58: Travaux de maçonnerie générale et gros œuvre de bâtiment | H58: 6 à 9 | I58: PAULX | J58: 44270 | K58: 44 | L58: recherche web (agent IA) | M58: façades : bardage, ITE, enduits | N58: https://www.pagesjaunes.fr/pros/00538340
A59: 353997968 | B59: CHARPENTE COUVERT BARDAGE ISOLATION (CCBI) | C59: Probable | F59: 43.32B | G59: Travaux de menuiserie métallique et serrurerie | H59: 6 à 9 | I59: JANS | J59: 44170 | K59: 44 | L59: non vérifié (quota de 200 recherches web atteint) | M59: mot-clé dans le nom/enseigne ; NAF 43.32B BTP cohérent
A60: 820568723 | B60: EC FACADE (EC FACADE) | C60: Probable | F60: 43.99C | G60: Travaux de maçonnerie générale et gros œuvre de bâtiment | H60: 6 à 9 | I60: SAINT-HERBLAIN | J60: 44800 | K60: 44 | L60: recherche web (agent IA) | M60: sources = annuaires uniquement | N60: https://www.societe.com/societe/ec-facade-820568723.html
A61: 893930438 | B61: GAVALAND BARDAGE | C61: Probable | F61: 43.91B | G61: Travaux de couverture par éléments | H61: 6 à 9 | I61: LE PALLET | J61: 44330 | K61: 44 | L61: non vérifié (quota de 200 recherches web atteint) | M61: mot-clé dans le nom/enseigne ; NAF 43.91B BTP cohérent
A62: 830139259 | B62: BARDAGE DU GATINAIS | C62: Probable | F62: 43.99A | G62: Travaux d'étanchéification | H62: 6 à 9 | I62: VILLEMANDEUR | J62: 45700 | K62: 45 | L62: non vérifié (quota de 200 recherches web atteint) | M62: mot-clé dans le nom/enseigne ; NAF 43.99A BTP cohérent
A63: 418734141 | B63: DA SILVA RAVALEMENT | C63: Probable | F63: 43.33Z | G63: Travaux de revêtement des sols et des murs | H63: 20 à 49 | I63: CLERY-SAINT-ANDRE | J63: 45370 | K63: 45 | L63: non vérifié (quota de 200 recherches web atteint) | M63: mot-clé dans le nom/enseigne ; NAF 43.33Z BTP cohérent
A64: 918168634 | B64: MF BARDAGE | C64: Probable | F64: 43.99A | G64: Travaux d'étanchéification | H64: 10 à 19 | I64: LA CHAPELLE-SAINT-MESMIN | J64: 45380 | K64: 45 | L64: non vérifié (quota de 200 recherches web atteint) | M64: mot-clé dans le nom/enseigne ; NAF 43.99A BTP cohérent
A65: 393677323 | B65: RAVALEMENT ORLEANAIS SARL | C65: Probable | F65: 43.39Z | G65: Autres travaux de finition | H65: 6 à 9 | I65: DARVOY | J65: 45150 | K65: 45 | L65: non vérifié (quota de 200 recherches web atteint) | M65: mot-clé dans le nom/enseigne ; NAF 43.39Z BTP cohérent
A66: 481125078 | B66: T.F RAVALEMENT SARL | C66: Probable | F66: 43.99C | G66: Travaux de maçonnerie générale et gros œuvre de bâtiment | H66: 6 à 9 | I66: ORLEANS | J66: 45100 | K66: 45 | L66: non vérifié (quota de 200 recherches web atteint) | M66: mot-clé dans le nom/enseigne ; NAF 43.99C BTP cohérent
A67: 882912470 | B67: EFS PROJETS | C67: Hors cible (autre métier) | E67: NE PAS PROSPECTER : liquidation judiciaire | F67: 43.32B | G67: Travaux de menuiserie métallique et serrurerie | H67: 10 à 19 | I67: BON-ENCONTRE | J67: 47240 | K67: 47 | L67: recherche web (agent IA) | M67: métallerie / menuiserie ; façade non attestée | N67: https://www.pappers.fr/entreprise/efs-projets-882912470
A68: 328845946 | B68: ANGEVINE DE RAVALEMENT ET DE TRAVAUX (ART) | C68: Probable | E68: NE PAS PROSPECTER : liquidation judiciaire | F68: 43.99C | G68: Travaux de maçonnerie générale et gros œuvre de bâtiment | H68: 6 à 9 | I68: ECOUFLANT | J68: 49000 | K68: 49 | L68: non vérifié (quota de 200 recherches web atteint) | M68: mot-clé dans le nom/enseigne ; NAF 43.99C BTP cohérent
A69: 390035400 | B69: AGENCE BRADFORD | C69: Hors cible | E69: Vigilance : redressement judiciaire en cours | F69: 74.10Z | G69: Activités spécialisées de design | H69: 20 à 49 | I69: LILLE | J69: 59800 | K69: 59 | L69: BODACC (activité déclarée au greffe) | M69: activité déclarée : agence de communication, créations graphiques (hors bâtiment) | N69: https://www.bodacc.fr/ (SIREN 390035400)
A70: 383929056 | B70: AUTO CONSULTANT | C70: Hors cible | E70: NE PAS PROSPECTER : liquidation judiciaire | F70: 70.22Z | G70: Conseil pour les affaires et autres conseils de gestion | H70: 20 à 49 | I70: LILLE | J70: 59800 | K70: 59 | L70: automatique (NAF hors BTP) | M70: NAF 70.22Z hors BTP
A71: 912219292 | B71: BARDAGE ET CO | C71: Probable | F71: 43.91B | G71: Travaux de couverture par éléments | H71: 10 à 19 | I71: LILLE | J71: 59800 | K71: 59 | L71: non vérifié (quota de 200 recherches web atteint) | M71: mot-clé dans le nom/enseigne ; NAF 43.91B BTP cohérent
A72: 524671260 | B72: DERNIER CRI | C72: Hors cible | F72: 62.01Z | G72: Programmation informatique | H72: 50 à 99 | I72: LILLE | J72: 59800 | K72: 59 | L72: automatique (NAF hors BTP) | M72: NAF 62.01Z hors BTP
A73: 478997216 | B73: DETOWIN | C73: Hors cible | F73: 47.42Z | G73: Commerce de détail de matériels de télécommunication en magasin spécialisé | H73: 20 à 49 | I73: LILLE | J73: 59800 | K73: 59 | L73: automatique (NAF hors BTP) + BODACC | M73: NAF 47.42Z hors BTP ; activité déclarée : Vente au dÃ©tail de matÃ©riel de tÃ©lÃ©communication et d'accessoires / Commerce d'achat et vente d'appareils de téléphonie filaires et mobiles et activités liées / Vente de téléphonie mobile. | N73: https://www.bodacc.fr/ (SIREN 478997216)
A74: 843355371 | B74: H.D.F. ENDUITS FACADES | C74: Probable | F74: 41.20A | G74: Construction de maisons individuelles | H74: 6 à 9 | I74: LILLE | J74: 59160 | K74: 59 | L74: recherche web (agent IA) | M74: sources = annuaires uniquement ; NAF maisons individuelles | N74: https://www.pappers.fr/entreprise/hdf-enduits-facades-843355371
A75: 437547888 | B75: LA PREVOYANCE | C75: Hors cible | F75: 87.30A | G75: Hébergement social pour personnes âgées | H75: 50 à 99 | I75: LILLE | J75: 59800 | K75: 59 | L75: automatique (NAF hors BTP) | M75: NAF 87.30A hors BTP
A76: 840181259 | B76: LE BUS MAGIQUE | C76: Hors cible | F76: 56.10A | G76: Restauration traditionnelle | H76: 6 à 9 | I76: LILLE | J76: 59000 | K76: 59 | L76: automatique (NAF hors BTP) | M76: NAF 56.10A hors BTP
A77: 508902004 | B77: MULTI-FACADES | C77: Confirmé | D77: Façadier (ravalement, enduits, ITE, bardage) | E77: NE PAS PROSPECTER : liquidation judiciaire | F77: 43.39Z | G77: Autres travaux de finition | H77: 6 à 9 | I77: DOUAI | J77: 59500 | K77: 59 | L77: recherche web (agent IA) | M77: ravalement de façades et toitures, ITE | N77: https://annuaire-entreprises.data.gouv.fr/entreprise/508902004 (source d'origine hors ligne au 26/09/2026 : https://www.multi-facades62.fr/contact)
A78: 751177353 | B78: RYU WOK (CLUBTROTTEUR) | C78: Hors cible | F78: 56.10A | G78: Restauration traditionnelle | H78: 6 à 9 | I78: LILLE | J78: 59800 | K78: 59 | L78: automatique (NAF hors BTP) + BODACC | M78: NAF 56.10A hors BTP ; activité déclarée : Restauration rapide | N78: https://www.bodacc.fr/ (SIREN 751177353)
A79: 484442652 | B79: SARL DES MINIMES (L ARRIERE PAYS) | C79: Hors cible | F79: 68.20B | G79: Location de terrains et d'autres biens immobiliers | H79: 6 à 9 | I79: LILLE | J79: 59800 | K79: 59 | L79: automatique (NAF hors BTP) | M79: NAF 68.20B hors BTP
A80: 315334573 | B80: SOCIETE DE RAVALEMENT DU CAMBRESIS (SRC) | C80: Probable | F80: 43.99C | G80: Travaux de maçonnerie générale et gros œuvre de bâtiment | H80: 10 à 19 | I80: SAINT-HILAIRE-LEZ-CAMBRAI | J80: 59292 | K80: 59 | L80: non vérifié (quota de 200 recherches web atteint) | M80: mot-clé dans le nom/enseigne ; NAF 43.99C BTP cohérent
A81: 812463792 | B81: BARDAGE ET COMPAGNIE | C81: Probable | F81: 43.91B | G81: Travaux de couverture par éléments | H81: 6 à 9 | I81: NOYON | J81: 60400 | K81: 60 | L81: non vérifié (quota de 200 recherches web atteint) | M81: mot-clé dans le nom/enseigne ; NAF 43.91B BTP cohérent
A82: 413180209 | B82: COUVERTURE BARDAGE RANSART - CBR (CBR) | C82: Probable | F82: 43.91B | G82: Travaux de couverture par éléments | H82: 6 à 9 | I82: RANSART | J82: 62173 | K82: 62 | L82: non vérifié (quota de 200 recherches web atteint) | M82: mot-clé dans le nom/enseigne ; NAF 43.91B BTP cohérent
A83: 890383052 | B83: LOOK FACADE | C83: Probable | F83: 43.29A | G83: Travaux d'isolation | H83: 10 à 19 | I83: NŒUX-LES-MINES | J83: 62290 | K83: 62 | L83: recherche web (agent IA) | M83: isolation (murs, combles, sols), RGE ; façade non explicite | N83: https://annuaire-entreprises.data.gouv.fr/entreprise/890383052 (source d'origine hors ligne au 26/09/2026 : https://artisanmalin.com/entreprises-disolation/noeux-les-mines/look-facade/)
A84: 828232272 | B84: R.H.D.F (RAVALEMENT HAUTS-DE-FRANCE) | C84: Confirmé | D84: Façadier (ravalement, enduits, ITE, bardage) | E84: NE PAS PROSPECTER : plan de cession | F84: 43.99A | G84: Travaux d'étanchéification | H84: 20 à 49 | I84: OUTREAU | J84: 62230 | K84: 62 | L84: BODACC (activité déclarée au greffe) | M84: activité déclarée : Peinture, ravalement, étanchéité de façades, revêtements et rénovation des sols et murs, isolation extérieure, bardage, vitrerie, achat et revente de biens mobiliers et immobiliers. | N84: https://www.bodacc.fr/ (SIREN 828232272)
A85: 878266899 | B85: RSN FACADE | C85: Confirmé | D85: Façadier (ravalement, enduits, ITE, bardage) | E85: NE PAS PROSPECTER : liquidation judiciaire | F85: 41.20A | G85: Construction de maisons individuelles | H85: 6 à 9 | I85: SALLAUMINES | J85: 62430 | K85: 62 | L85: recherche web (agent IA) | M85: ravalement, isolation, enduits | N85: https://www.pagesjaunes.fr/pros/60651429
A86: 801618364 | B86: C3 - BUREAU D'ETUDES FACADES (C3) | C86: Hors cible (adjacent) | F86: 71.12B | G86: Ingénierie, études techniques | H86: 6 à 9 | I86: BAYONNE | J86: 64100 | K86: 64 | L86: BODACC (activité déclarée au greffe) | M86: activité déclarée : bureau d'études bâtiment, maîtrise d'œuvre, expertises | N86: https://www.bodacc.fr/ (SIREN 801618364)
A87: 912726718 | B87: ENDUIT 66 FACADES | C87: Confirmé | D87: Façadier (ravalement, enduits, ITE, bardage) | E87: NE PAS PROSPECTER : liquidation judiciaire | F87: 43.99C | G87: Travaux de maçonnerie générale et gros œuvre de bâtiment | H87: 6 à 9 | I87: PERPIGNAN | J87: 66000 | K87: 66 | L87: recherche web (agent IA) | M87: enduits de façade (neuf et rénovation) | N87: https://www.enduit66facades.fr/
A88: 814555157 | B88: MS FACADE | C88: Confirmé | D88: Façadier (ravalement, enduits, ITE, bardage) | E88: NE PAS PROSPECTER : liquidation judiciaire | F88: 43.33Z | G88: Travaux de revêtement des sols et des murs | H88: 6 à 9 | I88: PIA | J88: 66380 | K88: 66 | L88: recherche web (agent IA) | M88: objet social : bardage et isolation de façades (direct ou sous-traitance) | N88: https://www.pappers.fr/entreprise/ms-facade-814555157
A89: 534723127 | B89: SARL RNS FACADES | C89: Confirmé | D89: Façadier (ravalement, enduits, ITE, bardage) | E89: NE PAS PROSPECTER : liquidation judiciaire | F89: 43.34Z | G89: Travaux de peinture et vitrerie | H89: 20 à 49 | I89: PERPIGNAN | J89: 66100 | K89: 66 | L89: recherche web (agent IA) | M89: ravalement de façades, peinture, revêtements | N89: https://www.rnsfacades.fr/
A90: 888838588 | B90: BIG RAVALEMENT (BIG RAVALEMENT) | C90: Confirmé | D90: Façadier (ravalement, enduits, ITE, bardage) | E90: NE PAS PROSPECTER : liquidation judiciaire | F90: 43.99C | G90: Travaux de maçonnerie générale et gros œuvre de bâtiment | H90: 6 à 9 | I90: STRASBOURG | J90: 67100 | K90: 67 | L90: recherche web (agent IA) | M90: ravalement, ITE, peinture ext. (RGE Qualibat) | N90: https://annuaire-entreprises.data.gouv.fr/entreprise/888838588 (source d'origine hors ligne au 26/09/2026 : https://www.big-ravalement.fr/)
A91: 832239610 | B91: DS RAVALEMENT (DS RAVALEMENT) | C91: Confirmé | D91: Façadier (ravalement, enduits, ITE, bardage) | E91: NE PAS PROSPECTER : liquidation judiciaire | F91: 43.99C | G91: Travaux de maçonnerie générale et gros œuvre de bâtiment | H91: 10 à 19 | I91: STRASBOURG | J91: 67100 | K91: 67 | L91: recherche web (agent IA) | M91: ravalement, ITE (RGE) | N91: https://annuaire-entreprises.data.gouv.fr/entreprise/832239610 (source d'origine hors ligne au 26/09/2026 : https://www.ds-ravalement.fr/)
A92: 799395207 | B92: EMAILLERIE ALSACIENNE (EA FACADE) | C92: Hors cible (autre métier) | F92: 25.11Z | G92: Fabrication de structures métalliques et de parties de structures | H92: 20 à 49 | I92: ALTORF | J92: 67120 | K92: 67 | L92: recherche web (agent IA) | M92: fabricant de panneaux de façade (émail/verre), pas poseur | N92: https://www.ea-facade.com/l-entreprise/
A93: 878826395 | B93: OPTICOD | C93: Hors cible | F93: 62.02A | G93: Conseil en systèmes et logiciels informatiques | H93: 10 à 19 | I93: VENDENHEIM | J93: 67550 | K93: 67 | L93: automatique (NAF hors BTP) | M93: NAF 62.02A hors BTP
A94: 898226519 | B94: PEINTURE ECKERT ECHAFAUDAGE ET RAVALEMENT (PEINTURE ECKERT ECHAFAUDAGE ET RAVALEMENT) | C94: Probable | F94: 43.34Z | G94: Travaux de peinture et vitrerie | H94: 6 à 9 | I94: BENNWIHR | J94: 68126 | K94: 68 | L94: non vérifié (quota de 200 recherches web atteint) | M94: mot-clé dans le nom/enseigne ; NAF 43.34Z BTP cohérent
A95: 851293969 | B95: SOCIETE DE RAVALEMENT ET PEINTURE SRP | C95: Douteux | F95: 43.34Z | G95: Travaux de peinture et vitrerie | H95: 20 à 49 | I95: MULHOUSE | J95: 68100 | K95: 68 | L95: BODACC (activité déclarée au greffe) | M95: activité déclarée sans mention façade : Travaux de peinture en bâtiment. | N95: https://www.bodacc.fr/ (SIREN 851293969)
A96: 800675126 | B96: 5E FACADE | C96: Hors cible (autre métier) | F96: 43.99A | G96: Travaux d'étanchéification | H96: 6 à 9 | I96: VILLEURBANNE | J96: 69100 | K96: 69 | L96: recherche web (agent IA) | M96: étancheur (« 5e façade » = toiture), pas façadier | N96: https://www.pagesjaunes.fr/pros/55941510
A97: 922615364 | B97: AGBE ETANCHEITE-BARDAGE (AGBE ETANCHEITE-BARDAGE) | C97: Confirmé | D97: Couvreur / étancheur faisant du bardage | E97: Vigilance : redressement judiciaire en cours | F97: 43.99A | G97: Travaux d'étanchéification | H97: 6 à 9 | I97: LYON | J97: 69003 | K97: 69 | L97: BODACC (activité déclarée au greffe) | M97: activité déclarée : activités d'étanchéité, couverture, bardage, réparation de fuites, travaux de charpente, nettoyage | N97: https://www.bodacc.fr/ (SIREN 922615364)
A98: 877955237 | B98: ALTITUDE FACADES ET BARDAGES (ALTITUDE FACADES ET BARDAGES) | C98: Douteux | F98: 43.29A | G98: Travaux d'isolation | H98: 6 à 9 | I98: SAINT-GENIS-LAVAL | J98: 69230 | K98: 69 | L98: recherche web (agent IA) | M98: activité décrite = isolation par insufflation (murs creux, combles) ; façade/bardage non attesté | N98: https://omizi.com/professionnel/altitude-facades-et-bardages
A99: 482094455 | B99: FACADES ALTITUDE (FACADES ALTITUDE) | C99: Douteux | F99: 43.99C | G99: Travaux de maçonnerie générale et gros œuvre de bâtiment | H99: 10 à 19 | I99: SATHONAY-CAMP | J99: 69580 | K99: 69 | L99: recherche web (agent IA) | M99: PagesJaunes le classe couvreur ; aucune trace d'activité façade | N99: https://www.pagesjaunes.fr/pros/09341370
A100: 914388350 | B100: HM COUVERTURE BARDAGE | C100: Probable | F100: 43.99A | G100: Travaux d'étanchéification | H100: 6 à 9 | I100: VAULX-EN-VELIN | J100: 69120 | K100: 69 | L100: non vérifié (quota de 200 recherches web atteint) | M100: mot-clé dans le nom/enseigne ; NAF 43.99A BTP cohérent
A101: 335119558 | B101: LE PETIT NEMO | C101: Hors cible | F101: 88.91A | G101: Accueil de jeunes enfants | H101: 10 à 19 | I101: VILLEURBANNE | J101: 69100 | K101: 69 | L101: automatique (NAF hors BTP) | M101: NAF 88.91A hors BTP
...

Sheet Base
A1: SIREN | B1: Nom | C1: Classement | D1: Spécialité | E1: Alerte | F1: Méthode de vérification | G1: Preuve | H1: Source | I1: Code NAF | J1: Libellé NAF | K1: Tranche effectif (code INSEE) | L1: Effectif (salariés) | M1: Commune | N1: Code postal | O1: Département | P1: Procédure collective (BODACC) | Q1: Date procédure | R1: Qualifications RGE valides | S1: Activité déclarée au greffe (BODACC) | T1: Date de création
A2: 851694190 | B2: CAVIEUX FACADES | C2: Confirmé | D2: Façadier (ravalement, enduits, ITE, bardage) | F2: automatique (RGE ADEME / site web) | G2: RGE isolation des murs par l'extérieur (ADEME) ; site web : enduit, facade, ite, ravalement ; mot-clé dans le nom/enseigne ; NAF 43.99C BTP cohérent | H2: https://data.ademe.fr/datasets/liste-des-entreprises-rge-2 | I2: 43.99C | J2: Travaux de maçonnerie générale et gros œuvre de bâtiment | K2: 03 | L2: 6 à 9 | M2: SAINT-ANDRE-DE-CORCY | N2: 01390 | O2: 01 | R2: Isolation des murs par l'extérieur | S2: ravalement de façades, isolation et peintures extérieures / ravalement de façades et isolation par l'extérieur | T2: 2019-06-07
A3: 419678396 | B3: E.R.T.B.I. (ERTBI FACADES ENVIRONNEMENT) | C3: Confirmé | D3: Multi-activité (façade parmi d'autres métiers) | F3: recherche web (agent IA) | G3: échafaudage + travaux de façade extérieure, plâtrerie (multi-activité) | H3: https://lyon-entreprises.com/Annuaire/ERTBI-FACADES-ENVIRONNEMENT-20427/coordonnees-caluire-et-cuire.html | I3: 43.99B | J3: Travaux de montage de structures métalliques | K3: 03 | L3: 6 à 9 | M3: CHARNOZ-SUR-AIN | N3: 01800 | O3: 01 | T3: 1998-08-01
A4: 538058041 | B4: REIS BARDAGE | C4: Confirmé | D4: Couvreur / étancheur faisant du bardage | F4: BODACC (activité déclarée au greffe) | G4: activité déclarée : Travaux de couverture et de bardage. | H4: https://www.bodacc.fr/ (SIREN 538058041) | I4: 43.91B | J4: Travaux de couverture par éléments | K4: 03 | L4: 6 à 9 | M4: LA BOISSE | N4: 01120 | O4: 01 | S4: Travaux de couverture et de bardage. | T4: 2011-11-15
A5: 915208334 | B5: TECHNO BARDAGE | C5: Confirmé | D5: Couvreur / étancheur faisant du bardage | F5: BODACC (activité déclarée au greffe) | G5: activité déclarée : couverture et bardage | H5: https://www.bodacc.fr/ (SIREN 915208334) | I5: 43.91B | J5: Travaux de couverture par éléments | K5: 03 | L5: 6 à 9 | M5: MONTLUEL | N5: 01120 | O5: 01 | S5: couverture et bardage | T5: 2022-07-15
A6: 828285437 | B6: CFP TECHNI-FACADES | C6: Confirmé | D6: Façadier (ravalement, enduits, ITE, bardage) | F6: automatique (RGE ADEME / site web) | G6: RGE isolation des murs par l'extérieur (ADEME) ; mot-clé dans le nom/enseigne ; NAF 43.99C BTP cohérent | H6: https://data.ademe.fr/datasets/liste-des-entreprises-rge-2 | I6: 43.99C | J6: Travaux de maçonnerie générale et gros œuvre de bâtiment | K6: 03 | L6: 6 à 9 | M6: BRUGHEAS | N6: 03700 | O6: 03 | R6: Isolation des murs par l'extérieur | S6: Ravalement de façades, isolation extérieure, projection d'enduit à la chaux, peinture, petite maçonnerie. | T6: 2017-03-08
A7: 978246767 | B7: DK FACADE ITE PEINTURE | C7: Confirmé | D7: Façadier (ravalement, enduits, ITE, bardage) | F7: recherche web (agent IA) | G7: ravalement, ITE, peinture | H7: https://servicesartisans.fr/services/facadier/manosque/dk-facade-ite-peinture-978246767 | I7: 43.99C | J7: Travaux de maçonnerie générale et gros œuvre de bâtiment | K7: 03 | L7: 6 à 9 | M7: MANOSQUE | N7: 04100 | O7: 04 | T7: 2023-08-01
A8: 814514162 | B8: K 2 (CONCEPT FACADES) | C8: Confirmé | D8: Façadier (ravalement, enduits, ITE, bardage) | F8: recherche web (agent IA) | G8: enseigne CONCEPT FACADES : ravalement, peinture, ITE ; 20-49 salariés | H8: https://annuaire-entreprises.data.gouv.fr/entreprise/814514162 | I8: 43.99C | J8: Travaux de maçonnerie générale et gros œuvre de bâtiment | K8: 12 | L8: 20 à 49 | M8: BIOT | N8: 06410 | O8: 06 | S8: Ravalement façades peinture isolation extérieure. | T8: 2015-09-11
A9: 847633633 | B9: SASU BATI PROJECT FACADES | C9: Confirmé | D9: Façadier (ravalement, enduits, ITE, bardage) | F9: recherche web (agent IA) | G9: ravalement / nettoyage de façades (+ négoce carrelage) | H9: https://www.pagesjaunes.fr/pros/60786535 | I9: 43.33Z | J9: Travaux de revêtement des sols et des murs | K9: 03 | L9: 6 à 9 | M9: ANTIBES | N9: 06600 | O9: 06 | T9: 2018-12-17
A10: 837629419 | B10: SILLA FACADES | C10: Confirmé | D10: Façadier (ravalement, enduits, ITE, bardage) | F10: recherche web (agent IA) | G10: travaux de façade : nettoyage, isolation thermique | H10: https://www.pagesjaunes.fr/pros/55671292 | I10: 43.99C | J10: Travaux de maçonnerie générale et gros œuvre de bâtiment | K10: 12 | L10: 20 à 49 | M10: CAGNES-SUR-MER | N10: 06800 | O10: 06 | S10: Enduit de façade carrelage maçonnerie chape fluide | T10: 2018-02-01
A11: 819985979 | B11: FACADES A.Z. | C11: Confirmé | D11: Façadier (ravalement, enduits, ITE, bardage) | F11: automatique (RGE ADEME / site web) | G11: RGE isolation des murs par l'extérieur (ADEME) ; mot-clé dans le nom/enseigne ; NAF 43.99C BTP cohérent | H11: https://data.ademe.fr/datasets/liste-des-entreprises-rge-2 | I11: 43.99C | J11: Travaux de maçonnerie générale et gros œuvre de bâtiment | K11: 11 | L11: 10 à 19 | M11: SAINT-DIDIER-SOUS-AUBENAS | N11: 07200 | O11: 07 | R11: Isolation des murs par l'extérieur | Isolation des planchers bas | S11: Façades, isolations par l'extérieur, locations de matériels, pose de tous types de revêtements pour murs extérieurs | T11: 2016-04-15
A12: 433256237 | B12: FACADES ARDECHOISES | C12: Confirmé | D12: Façadier (ravalement, enduits, ITE, bardage) | F12: automatique (RGE ADEME / site web) | G12: RGE isolation des murs par l'extérieur (ADEME) ; site web : enduit, ravalement ; mot-clé dans le nom/enseigne ; NAF 43.99A BTP cohérent | H12: https://data.ademe.fr/datasets/liste-des-entreprises-rge-2 | I12: 43.99A | J12: Travaux d'étanchéification | K12: 12 | L12: 20 à 49 | M12: ANNONAY | N12: 07100 | O12: 07 | R12: Isolation des murs par l'extérieur | Isolation des planchers bas | T12: 2000-10-01
A13: 798080495 | B13: SUD ARDECHE FACADES | C13: Confirmé | D13: Façadier (ravalement, enduits, ITE, bardage) | F13: automatique (RGE ADEME / site web) | G13: RGE isolation des murs par l'extérieur (ADEME) ; mot-clé dans le nom/enseigne ; NAF 43.99C BTP cohérent | H13: https://data.ademe.fr/datasets/liste-des-entreprises-rge-2 | I13: 43.99C | J13: Travaux de maçonnerie générale et gros œuvre de bâtiment | K13: 03 | L13: 6 à 9 | M13: AUBENAS | N13: 07200 | O13: 07 | R13: Isolation des murs par l'extérieur | Isolation des planchers bas | Isolation par l'intérieur des murs ou rampants de toitures ou plafonds | S13: Maçonnerie générale, travaux de façade | T13: 2013-09-01
A14: 432863348 | B14: VIVARAIS FACADES ET RENOVATION | C14: Confirmé | D14: Façadier (ravalement, enduits, ITE, bardage) | F14: automatique (RGE ADEME / site web) | G14: RGE isolation des murs par l'extérieur (ADEME) ; mot-clé dans le nom/enseigne ; NAF 43.99C BTP cohérent | H14: https://data.ademe.fr/datasets/liste-des-entreprises-rge-2 | I14: 43.99C | J14: Travaux de maçonnerie générale et gros œuvre de bâtiment | K14: 11 | L14: 10 à 19 | M14: LACHAPELLE-SOUS-AUBENAS | N14: 07200 | O14: 07 | R14: Isolation des murs par l'extérieur | Isolation des toitures terrasses ou des toitures par l'extérieur | T14: 2000-08-07
A15: 511643827 | B15: ARIEGE ENDUIT FACADES (AEF) | C15: Confirmé | D15: Façadier (ravalement, enduits, ITE, bardage) | F15: automatique (RGE ADEME / site web) | G15: RGE isolation des murs par l'extérieur (ADEME) ; site web : bardage, enduit, facade, facadier, isolation thermique exterieur, ravalement ; mot-clé dans le nom/enseigne ; NAF 43.99D BTP cohérent | H15: https://data.ademe.fr/datasets/liste-des-entreprises-rge-2 | I15: 43.99D | J15: Autres travaux spécialisés de construction | K15: 03 | L15: 6 à 9 | M15: BENAGUES | N15: 09100 | O15: 09 | R15: Isolation des murs par l'extérieur | S15: Rénovation de façades construction et entretien d'immeubles maçonnerie plâtrerie pose de couverture,charpente,revêtements de sols et murs tous travaux | T15: 2009-04-06
A16: 900135211 | B16: PRO FACADE ISOLATION | C16: Confirmé | D16: Façadier (ravalement, enduits, ITE, bardage) | F16: recherche web (agent IA) | G16: isolation ext./int., travaux de façade, peinture | H16: https://www.pagesjaunes.fr/pros/62566720 | I16: 43.29A | J16: Travaux d'isolation | K16: 03 | L16: 6 à 9 | M16: SAINT-GIRONS | N16: 09200 | O16: 09 | S16: Isolation extérieure et intérieure, façade, peinture, petite maçonnerie, installation cloisons mobiles placoplâtre, pose de tâpisserie, vente menuiserie alu, bois et pvc | T16: 2021-05-28
A17: 789359205 | B17: BITETTI FACADE | C17: Confirmé | D17: Façadier (ravalement, enduits, ITE, bardage) | F17: recherche web (agent IA) | G17: enduits de façade, ravalement, maçonnerie | H17: https://www.artisans-du-batiment.com/artisan/bitetti-facade/ | I17: 43.99C | J17: Travaux de maçonnerie générale et gros œuvre de bâtiment | K17: 03 | L17: 6 à 9 | M17: VILLACERF | N17: 10600 | O17: 10 | S17: Ravalement, enduit de façade, travaux de maçonnerie | T17: 2012-11-02
A18: 389192949 | B18: DROUOT RAVALEMENT DE FACADES | C18: Confirmé | D18: Façadier (ravalement, enduits, ITE, bardage) | F18: recherche web (agent IA) | G18: ravalement de façades, enduits (Weber) | H18: https://annuaire-entreprises.data.gouv.fr/entreprise/389192949 (source d'origine hors ligne au 26/09/2026 : https://www.drouot-ravalement.com/ravalementfacades-pouan-les-vallees) | I18: 43.31Z | J18: Travaux de plâtrerie | K18: 03 | L18: 6 à 9 | M18: POUAN-LES-VALLEES | N18: 10700 | O18: 10 | T18: 1992-11-18
A19: 319265922 | B19: LAMBLIN DECORS ET FACADES | C19: Confirmé | D19: Façadier (ravalement, enduits, ITE, bardage) | F19: automatique (RGE ADEME / site web) | G19: RGE isolation des murs par l'extérieur (ADEME) ; site web : facade, isolation exterieur, isolation thermique exterieur, ravalement ; mot-clé dans le nom/enseigne ; NAF 43.34Z BTP cohérent | H19: https://data.ademe.fr/datasets/liste-des-entreprises-rge-2 | I19: 43.34Z | J19: Travaux de peinture et vitrerie | K19: 12 | L19: 20 à 49 | M19: BREVIANDES | N19: 10450 | O19: 10 | R19: Isolation des murs par l'extérieur | T19: 1980-07-01
A20: 878467125 | B20: ENDUIT FACADE NARBONNAIS (ENDUIT FACADE NARBONNAIS) | C20: Confirmé | D20: Façadier (ravalement, enduits, ITE, bardage) | F20: automatique (RGE ADEME / site web) | G20: RGE isolation des murs par l'extérieur (ADEME) ; mot-clé dans le nom/enseigne ; NAF 43.99C BTP cohérent | H20: https://data.ademe.fr/datasets/liste-des-entreprises-rge-2 | I20: 43.99C | J20: Travaux de maçonnerie générale et gros œuvre de bâtiment | K20: 03 | L20: 6 à 9 | M20: COURSAN | N20: 11110 | O20: 11 | R20: Isolation des murs par l'extérieur | T20: 2019-10-21
A21: 443613559 | B21: EURL FERCHAL RAVALEMENT | C21: Confirmé | D21: Façadier (ravalement, enduits, ITE, bardage) | F21: automatique (RGE ADEME / site web) | G21: RGE isolation des murs par l'extérieur (ADEME) ; mot-clé dans le nom/enseigne ; NAF 43.39Z BTP cohérent | H21: https://data.ademe.fr/datasets/liste-des-entreprises-rge-2 | I21: 43.39Z | J21: Autres travaux de finition | K21: 11 | L21: 10 à 19 | M21: MALVES-EN-MINERVOIS | N21: 11600 | O21: 11 | R21: Isolation des murs par l'extérieur | T21: 2002-10-01
A22: 441446408 | B22: FACADES D AUJORD HUI | C22: Confirmé | D22: Façadier (ravalement, enduits, ITE, bardage) | F22: automatique (RGE ADEME / site web) | G22: RGE isolation des murs par l'extérieur (ADEME) ; mot-clé dans le nom/enseigne ; NAF 43.99D BTP cohérent | H22: https://data.ademe.fr/datasets/liste-des-entreprises-rge-2 | I22: 43.99D | J22: Autres travaux spécialisés de construction | K22: 03 | L22: 6 à 9 | M22: LABASTIDE-D'ANJOU | N22: 11320 | O22: 11 | R22: Isolation des murs par l'extérieur | T22: 2002-02-28
A23: 309346310 | B23: LES RAVALEMENTS 2000 | C23: Confirmé | D23: Façadier (ravalement, enduits, ITE, bardage) | F23: automatique (RGE ADEME / site web) | G23: RGE isolation des murs par l'extérieur (ADEME) ; mot-clé dans le nom/enseigne ; NAF 43.39Z BTP cohérent | H23: https://data.ademe.fr/datasets/liste-des-entreprises-rge-2 | I23: 43.39Z | J23: Autres travaux de finition | K23: 11 | L23: 10 à 19 | M23: CARCASSONNE | N23: 11000 | O23: 11 | R23: Isolation des murs par l'extérieur | T23: 1977-01-01
A24: 790298558 | B24: OZBEK FACADES (OZBEK FACADES) | C24: Confirmé | D24: Façadier (ravalement, enduits, ITE, bardage) | F24: recherche web (agent IA) | G24: ravalement de façades (PagesJaunes), RGE Qualibat | H24: https://www.pagesjaunes.fr/pros/54514091 | I24: 43.99C | J24: Travaux de maçonnerie générale et gros œuvre de bâtiment | K24: 03 | L24: 6 à 9 | M24: COURSAN | N24: 11110 | O24: 11 | S24: Ravalement de façades | T24: 2013-01-01
A25: 891420622 | B25: EURL I 2 R FACADES | C25: Confirmé | D25: Façadier (ravalement, enduits, ITE, bardage) | F25: automatique (RGE ADEME / site web) | G25: RGE isolation des murs par l'extérieur (ADEME) ; mot-clé dans le nom/enseigne ; NAF 43.99C BTP cohérent | H25: https://data.ademe.fr/datasets/liste-des-entreprises-rge-2 | I25: 43.99C | J25: Travaux de maçonnerie générale et gros œuvre de bâtiment | K25: 03 | L25: 6 à 9 | M25: SAVIGNAC | N25: 12200 | O25: 12 | R25: Isolation des murs par l'extérieur | T25: 2020-11-25
A26: 514936046 | B26: EURO FACADES SALVAN (EURO FACADES SALVAN) | C26: Confirmé | D26: Façadier (ravalement, enduits, ITE, bardage) | F26: automatique (RGE ADEME / site web) | G26: RGE isolation des murs par l'extérieur (ADEME) ; site web : enduit, facade, facadier, isolation exterieur, ite, ravalement ; mot-clé dans le nom/enseigne ; NAF 43.99C BTP cohérent | H26: https://data.ademe.fr/datasets/liste-des-entreprises-rge-2 | I26: 43.99C | J26: Travaux de maçonnerie générale et gros œuvre de bâtiment | K26: 11 | L26: 10 à 19 | M26: CREISSELS | N26: 12100 | O26: 12 | R26: Isolation des murs par l'extérieur | S26: ravalement de façades, imperméabilisation, isolation, rénovation, peinture et travaux de finition, crépis | T26: 2009-09-21
A27: 500852819 | B27: FACADE ALU'12 | C27: Confirmé | D27: Façadier (ravalement, enduits, ITE, bardage) | F27: automatique (RGE ADEME / site web) | G27: RGE isolation des murs par l'extérieur (ADEME) ; site web : crepi, enduit, facade, isolation exterieur, ravalement, veture ; mot-clé dans le nom/enseigne ; NAF 43.29A BTP cohérent | H27: https://data.ademe.fr/datasets/liste-des-entreprises-rge-2 | I27: 43.29A | J27: Travaux d'isolation | K27: 11 | L27: 10 à 19 | M27: ONET-LE-CHATEAU | N27: 12850 | O27: 12 | P27: Plan de redressement | Q27: 2017-01-31 | R27: Isolation des combles perdus | Isolation des murs par l'extérieur | S27: Vente et pose de systèmes de protection et d'isolation de façades et de systèmes d'isolation thermique pour le bâtiment | T27: 2007-11-01
A28: 517509964 | B28: ALPILLES FACADES | C28: Confirmé | D28: Façadier (ravalement, enduits, ITE, bardage) | F28: automatique (RGE ADEME / site web) | G28: RGE isolation des murs par l'extérieur (ADEME) ; site web : facade, facadier ; mot-clé dans le nom/enseigne ; NAF 43.99A BTP cohérent | H28: https://data.ademe.fr/datasets/liste-des-entreprises-rge-2 | I28: 43.99A | J28: Travaux d'étanchéification | K28: 03 | L28: 6 à 9 | M28: MIRAMAS | N28: 13140 | O28: 13 | R28: Isolation des murs par l'extérieur | T28: 2009-10-01
A29: 839830775 | B29: BRIZZI FACADES | C29: Confirmé | D29: Façadier (ravalement, enduits, ITE, bardage) | F29: automatique (RGE ADEME / site web) | G29: RGE isolation des murs par l'extérieur (ADEME) ; mot-clé dans le nom/enseigne ; NAF 43.99C BTP cohérent | H29: https://data.ademe.fr/datasets/liste-des-entreprises-rge-2 | I29: 43.99C | J29: Travaux de maçonnerie générale et gros œuvre de bâtiment | K29: 03 | L29: 6 à 9 | M29: ROQUEVAIRE | N29: 13360 | O29: 13 | R29: Isolation des murs par l'extérieur | S29: ravalement de façades maçonnerie générale peinture rénovation étanchéité de terrasses. | T29: 2018-05-19
A30: 823681432 | B30: D.F.I DECO, FACADE, ISOLATION | C30: Confirmé | D30: Façadier (ravalement, enduits, ITE, bardage) | F30: recherche web (agent IA) | G30: ravalement de façades, ITE, maçonnerie | H30: https://www.pagesjaunes.fr/pros/58522379 | I30: 43.99C | J30: Travaux de maçonnerie générale et gros œuvre de bâtiment | K30: 03 | L30: 6 à 9 | M30: LANCON-PROVENCE | N30: 13680 | O30: 13 | T30: 2016-10-14
A31: 519518807 | B31: EURL FACADE PRO | C31: Confirmé | D31: Façadier (ravalement, enduits, ITE, bardage) | F31: automatique (RGE ADEME / site web) | G31: RGE isolation des murs par l'extérieur (ADEME) ; mot-clé dans le nom/enseigne ; NAF 43.99D BTP cohérent | H31: https://data.ademe.fr/datasets/liste-des-entreprises-rge-2 | I31: 43.99D | J31: Autres travaux spécialisés de construction | K31: 11 | L31: 10 à 19 | M31: AUBAGNE | N31: 13400 | O31: 13 | R31: Isolation des murs par l'extérieur | T31: 2010-01-01
A32: 884361817 | B32: I.P.F IDRISSI PRO FACADE | C32: Confirmé | D32: Façadier (ravalement, enduits, ITE, bardage) | F32: recherche web (agent IA) | G32: rénovation de façades, peinture/enduits | H32: https://www.pagesjaunes.fr/pros/62279084 | I32: 43.34Z | J32: Travaux de peinture et vitrerie | K32: 03 | L32: 6 à 9 | M32: CHATEAURENARD | N32: 13160 | O32: 13 | T32: 2020-06-18
A33: 853161982 | B33: L.B.P MEDITERRANEE FACADES | C33: Confirmé | D33: Façadier (ravalement, enduits, ITE, bardage) | F33: automatique (RGE ADEME / site web) | G33: RGE isolation des murs par l'extérieur (ADEME) ; mot-clé dans le nom/enseigne ; NAF 43.99C BTP cohérent | H33: https://data.ademe.fr/datasets/liste-des-entreprises-rge-2 | I33: 43.99C | J33: Travaux de maçonnerie générale et gros œuvre de bâtiment | K33: 11 | L33: 10 à 19 | M33: AIX EN PROVENCE | N33: 13080 | O33: 13 | R33: Isolation des murs par l'extérieur | S33: tous travaux dans le bâtiment et rénovation de façades / tous travaux dans le bâtiment et rénovation de façades. | T33: 2019-07-25
A34: 493598965 | B34: LA FACADE PROVENCALE (LE SAVOIR FAIRE AU S) | C34: Confirmé | D34: Façadier (ravalement, enduits, ITE, bardage) | F34: automatique (RGE ADEME / site web) | G34: RGE isolation des murs par l'extérieur (ADEME) ; mot-clé dans le nom/enseigne ; NAF 43.34Z BTP cohérent | H34: https://data.ademe.fr/datasets/liste-des-entreprises-rge-2 | I34: 43.34Z | J34: Travaux de peinture et vitrerie | K34: 03 | L34: 6 à 9 | M34: MARSEILLE | N34: 13015 | O34: 13 | R34: Isolation des murs par l'extérieur | T34: 2007-01-05
A35: 420586067 | B35: MARSEILLE FACADES | C35: Confirmé | D35: Façadier (ravalement, enduits, ITE, bardage) | F35: automatique (RGE ADEME / site web) | G35: RGE isolation des murs par l'extérieur (ADEME) ; mot-clé dans le nom/enseigne ; NAF 43.33Z BTP cohérent | H35: https://data.ademe.fr/datasets/liste-des-entreprises-rge-2 | I35: 43.33Z | J35: Travaux de revêtement des sols et des murs | K35: 03 | L35: 6 à 9 | M35: MARSEILLE | N35: 13010 | O35: 13 | R35: Chauffe-Eau Thermodynamique | Isolation des murs par l'extérieur | Pompe à chaleur : chauffage | T35: 1998-11-01
A36: 430459016 | B36: PROVENCE FACADES MEDITERRANEE | C36: Confirmé | D36: Façadier (ravalement, enduits, ITE, bardage) | F36: automatique (RGE ADEME / site web) | G36: RGE isolation des murs par l'extérieur (ADEME) ; site web : facade, isolation exterieur, isolation thermique par l'exterieur, ite, ravalement ; mot-clé dans le nom/enseigne ; NAF 43.99C BTP cohérent | H36: https://data.ademe.fr/datasets/liste-des-entreprises-rge-2 | I36: 43.99C | J36: Travaux de maçonnerie générale et gros œuvre de bâtiment | K36: 12 | L36: 20 à 49 | M36: ROQUEFORT-LA-BEDOULE | N36: 13830 | O36: 13 | R36: Isolation des murs par l'extérieur | T36: 2000-05-01
A37: 849891528 | B37: PROVENCE RAVALEMENT PEINTURE | C37: Confirmé | D37: Façadier (ravalement, enduits, ITE, bardage) | F37: automatique (RGE ADEME / site web) | G37: RGE isolation des murs par l'extérieur (ADEME) ; mot-clé dans le nom/enseigne ; NAF 43.99C BTP cohérent | H37: https://data.ademe.fr/datasets/liste-des-entreprises-rge-2 | I37: 43.99C | J37: Travaux de maçonnerie générale et gros œuvre de bâtiment | K37: 11 | L37: 10 à 19 | M37: MARSEILLE | N37: 13014 | O37: 13 | R37: Isolation des murs par l'extérieur | Isolation par l'intérieur des murs ou rampants de toitures ou plafonds | S37: travaux de maçonnerie générale peinture ravalement revêtement sol et mur. | T37: 2019-04-09
A38: 329934889 | B38: SOC ISOLATION ET DE PEINTURE (SIP) | C38: Confirmé | D38: Façadier (ravalement, enduits, ITE, bardage) | F38: automatique (RGE ADEME / site web) | G38: RGE isolation des murs par l'extérieur (ADEME) ; NAF 43.34Z BTP cohérent | H38: https://data.ademe.fr/datasets/liste-des-entreprises-rge-2 | I38: 43.34Z | J38: Travaux de peinture et vitrerie | K38: 21 | L38: 50 à 99 | M38: MARSEILLE | N38: 13011 | O38: 13 | R38: Isolation des murs par l'extérieur | Isolation des planchers bas | S38: désamiantage, décontamination, encapsulage de l'amiante et de commercialisation de services d'enlèvement. | T38: 1984-05-01
A39: 409146180 | B39: SOCIETE D'ISOLATION ET DE RAVALEMENT ANDRE MOULINET (SIRAM) | C39: Confirmé | D39: Façadier (ravalement, enduits, ITE, bardage) | F39: automatique (RGE ADEME / site web) | G39: RGE isolation des murs par l'extérieur (ADEME) ; site web : bardage, facade, isolation exterieur, ravalement ; mot-clé dans le nom/enseigne ; NAF 43.32A BTP cohérent | H39: https://data.ademe.fr/datasets/liste-des-entreprises-rge-2 | I39: 43.32A | J39: Travaux de menuiserie bois et PVC | K39: 03 | L39: 6 à 9 | M39: SANNERVILLE | N39: 14940 | O39: 14 | R39: Fenêtres, volets, portes donnant sur l'extérieur | Isolation des murs par l'extérieur | S39: Pose, isolation, ravalement,peinture et tous travaux se rapportant au bâtiment (achat d'un fonds artisanal) | T39: 1996-10-03
A40: 342526019 | B40: CREPIS FACADE CONSTRUCTION (CFC) | C40: Confirmé | D40: Façadier (ravalement, enduits, ITE, bardage) | F40: automatique (RGE ADEME / site web) | G40: RGE isolation des murs par l'extérieur (ADEME) ; site web : enduit, facade, facadier, isolation exterieur, isolation par l'exterieur, ite, ravalement ; mot-clé dans le nom/enseigne ; NAF 43.29A BTP cohérent | H40: https://data.ademe.fr/datasets/liste-des-entreprises-rge-2 | I40: 43.29A | J40: Travaux d'isolation | K40: 12 | L40: 20 à 49 | M40: RUELLE-SUR-TOUVRE | N40: 16600 | O40: 16 | R40: Isolation des murs par l'extérieur | S40: projection de mousse polyuréthane | T40: 1987-10-01
A41: 418778726 | B41: EURL FACADES SARTORI HERVE (CFC FACADES COGNAC) | C41: Confirmé | D41: Façadier (ravalement, enduits, ITE, bardage) | F41: automatique (RGE ADEME / site web) | G41: RGE isolation des murs par l'extérieur (ADEME) ; mot-clé dans le nom/enseigne ; NAF 43.99C BTP cohérent | H41: https://data.ademe.fr/datasets/liste-des-entreprises-rge-2 | I41: 43.99C | J41: Travaux de maçonnerie générale et gros œuvre de bâtiment | K41: 11 | L41: 10 à 19 | M41: GENSAC-LA-PALLUE | N41: 16130 | O41: 16 | R41: Isolation des murs par l'extérieur | T41: 1998-04-07
A42: 419007661 | B42: ENTREPRISE SUIRE RAVALEMENT PEINTURE | C42: Confirmé | D42: Façadier (ravalement, enduits, ITE, bardage) | F42: automatique (RGE ADEME / site web) | G42: RGE isolation des murs par l'extérieur (ADEME) ; mot-clé dans le nom/enseigne ; NAF 43.39Z BTP cohérent | H42: https://data.ademe.fr/datasets/liste-des-entreprises-rge-2 | I42: 43.39Z | J42: Autres travaux de finition | K42: 03 | L42: 6 à 9 | M42: THORS | N42: 17160 | O42: 17 | R42: Isolation des murs par l'extérieur | T42: 1998-04-01
A43: 522671809 | B43: I.T.F. ISOLATION TOITURE FACADE | C43: Confirmé | D43: Façadier (ravalement, enduits, ITE, bardage) | F43: automatique (RGE ADEME / site web) | G43: RGE isolation des murs par l'extérieur (ADEME) ; mot-clé dans le nom/enseigne ; NAF 43.29A BTP cohérent | H43: https://data.ademe.fr/datasets/liste-des-entreprises-rge-2 | I43: 43.29A | J43: Travaux d'isolation | K43: 03 | L43: 6 à 9 | M43: JONZAC | N43: 17500 | O43: 17 | R43: Fenêtres, volets, portes donnant sur l'extérieur | Isolation des combles perdus | Isolation des murs par l'extérieur | Isolation des planchers bas | S43: Isolation des combles, la vente et la pose d'isolation, le nettoyage et la rénovation des toitures, le ravalement de façade | T43: 2010-05-03
A44: 409596244 | B44: NOUVELLE AQUITAINE RAVALEMENT (NAR) | C44: Confirmé | D44: Façadier (ravalement, enduits, ITE, bardage) | E44: Radiée au BODACC | F44: automatique (RGE ADEME / site web) | G44: RGE isolation des murs par l'extérieur (ADEME) ; mot-clé dans le nom/enseigne ; NAF 43.34Z BTP cohérent | H44: https://data.ademe.fr/datasets/liste-des-entreprises-rge-2 | I44: 43.34Z | J44: Travaux de peinture et vitrerie | K44: 11 | L44: 10 à 19 | M44: ROYAN | N44: 17200 | O44: 17 | R44: Isolation des murs par l'extérieur | S44: peinture, revêtements de sols et murs ravalement décoration, vitrerie / tous travaux de revêtement de façade, imperméabili sation, étanchéité, isolation, peinture,projection de tous matériaux sur tous supports, pose de revê- tements sur murs et sols, réfection des bétons par mortier synthétique | T44: 1996-11-04
A45: 844247460 | B45: RAVALEMENT DE FRANCE 44 (R.D.F. 44) | C45: Confirmé | D45: Façadier (ravalement, enduits, ITE, bardage) | E45: NE PAS PROSPECTER : liquidation judiciaire | F45: BODACC (activité déclarée au greffe) | G45: activité déclarée : réalisation d'enduit de façades de sablage de façades nettoyage de façades peinture en bâtiment | H45: https://www.bodacc.fr/ (SIREN 844247460) | I45: 43.39Z | J45: Autres travaux de finition | K45: 11 | L45: 10 à 19 | M45: SAINT-MEDARD-D'AUNIS | N45: 17220 | O45: 17 | P45: Liquidation judiciaire | Q45: 2025-04-22 | S45: réalisation d'enduit de façades de sablage de façades nettoyage de façades peinture en bâtiment | T45: 2018-11-22
A46: 797834348 | B46: S.A.R.L. RAVALEMENTS DE SAINTONGE R.V.S. | C46: Confirmé | D46: Multi-activité (façade parmi d'autres métiers) | F46: recherche web (agent IA) | G46: peinture int./ext. dont ravalement de façades (multi-activité peinture) | H46: https://www.pagesjaunes.fr/pros/58680817 | I46: 43.39Z | J46: Autres travaux de finition | K46: 03 | L46: 6 à 9 | M46: PONS | N46: 17800 | O46: 17 | T46: 2013-10-15
A47: 790536361 | B47: A.R.B FACADES (A.R.B FACADES) | C47: Confirmé | D47: Façadier (ravalement, enduits, ITE, bardage) | F47: automatique (RGE ADEME / site web) | G47: RGE isolation des murs par l'extérieur (ADEME) ; mot-clé dans le nom/enseigne ; NAF 43.99C BTP cohérent | H47: https://data.ademe.fr/datasets/liste-des-entreprises-rge-2 | I47: 43.99C | J47: Travaux de maçonnerie générale et gros œuvre de bâtiment | K47: 11 | L47: 10 à 19 | M47: NOAILLES | N47: 19600 | O47: 19 | P47: Plan de redressement | Q47: 2026-04-24 | R47: Isolation des murs par l'extérieur | S47: ravalement isolation bardage maçonnerie et tous travaux du bâtiment s'y rapportant. | T47: 2013-01-15
A48: 842745028 | B48: BARDAGE EXTERIEUR ISOLATION - EN ABREGE : BEI (BEI) | C48: Confirmé | D48: Façadier (ravalement, enduits, ITE, bardage) | F48: BODACC (activité déclarée au greffe) | G48: activité déclarée : Fourniture et pose de tous types de bardage; Couverture et isolation thermique par l'extérieur pour tous bâtiments | H48: https://www.bodacc.fr/ (SIREN 842745028) | I48: 43.33Z | J48: Travaux de revêtement des sols et des murs | K48: 03 | L48: 6 à 9 | M48: DIJON | N48: 21000 | O48: 21 | S48: Fourniture et pose de tous types de bardage; Couverture et isolation thermique par l'extérieur pour tous bâtiments | T48: 2018-09-13
A49: 827462490 | B49: FACADES BOURGOGNE 21 | C49: Confirmé | D49: Façadier (ravalement, enduits, ITE, bardage) | F49: automatique (RGE ADEME / site web) | G49: RGE isolation des murs par l'extérieur (ADEME) ; mot-clé dans le nom/enseigne ; NAF 43.99C BTP cohérent | H49: https://data.ademe.fr/datasets/liste-des-entreprises-rge-2 | I49: 43.99C | J49: Travaux de maçonnerie générale et gros œuvre de bâtiment | K49: 11 | L49: 10 à 19 | M49: CHENOVE | N49: 21300 | O49: 21 | R49: Isolation des murs par l'extérieur | S49: Ravalement de façades - isolation thermique | T49: 2016-07-01
A50: 512687047 | B50: ISOLATION FACADE MYRAL (I.F.M) | C50: Confirmé | D50: Façadier (ravalement, enduits, ITE, bardage) | F50: automatique (RGE ADEME / site web) | G50: RGE isolation des murs par l'extérieur (ADEME) ; site web : facade, isolation thermique par l'exterieur, ite ; mot-clé dans le nom/enseigne ; NAF 43.29A BTP cohérent | H50: https://data.ademe.fr/datasets/liste-des-entreprises-rge-2 | I50: 43.29A | J50: Travaux d'isolation | K50: 12 | L50: 20 à 49 | M50: IS-SUR-TILLE | N50: 21120 | O50: 21 | R50: Isolation des murs par l'extérieur | S50: Étude et réalisation de travaux d'isolation thermique, acoustique et antivibratique, bardage métallique, ignifugation, travaux d'isolation de canalisation de chauffage ou réfrigération, prise de tous procédés, brevets, le tout en sédentaire et en ambulant | T50: 2009-05-02
A51: 903997427 | B51: NP FACADE | C51: Confirmé | D51: Façadier (ravalement, enduits, ITE, bardage) | F51: recherche web (agent IA) | G51: ravalement de façades, peinture int./ext. | H51: https://www.societe.com/societe/np-facade-903997427.html | I51: 43.99C | J51: Travaux de maçonnerie générale et gros œuvre de bâtiment | K51: 03 | L51: 6 à 9 | M51: CHENOVE | N51: 21300 | O51: 21 | T51: 2021-10-01
A52: 424757276 | B52: PEINTURE ISOLATION ENDUIT RAVALEMENT (PIER) | C52: Confirmé | D52: Façadier (ravalement, enduits, ITE, bardage) | F52: automatique (RGE ADEME / site web) | G52: RGE isolation des murs par l'extérieur (ADEME) ; site web : crepi, enduit, facade, facadier, isolation thermique exterieur, ite, ravalement ; mot-clé dans le nom/enseigne ; NAF 43.39Z BTP cohérent | H52: https://data.ademe.fr/datasets/liste-des-entreprises-rge-2 | I52: 43.39Z | J52: Autres travaux de finition | K52: 12 | L52: 20 à 49 | M52: SAINT-USAGE | N52: 21170 | O52: 21 | R52: Isolation des murs par l'extérieur | T52: 1999-10-19
A53: 899002505 | B53: RAVALEMENT PEINTURE ISOLATION 21 (RPI 21) (RPI 21) | C53: Confirmé | D53: Façadier (ravalement, enduits, ITE, bardage) | F53: automatique (RGE ADEME / site web) | G53: RGE isolation des murs par l'extérieur (ADEME) ; mot-clé dans le nom/enseigne ; NAF 43.99D BTP cohérent | H53: https://data.ademe.fr/datasets/liste-des-entreprises-rge-2 | I53: 43.99D | J53: Autres travaux spécialisés de construction | K53: 03 | L53: 6 à 9 | M53: CHENOVE | N53: 21300 | O53: 21 | R53: Isolation des murs par l'extérieur | T53: 2021-04-15
A54: 395297773 | B54: ARMOR PEINTURE | C54: Confirmé | D54: Façadier (ravalement, enduits, ITE, bardage) | F54: automatique (RGE ADEME / site web) | G54: RGE isolation des murs par l'extérieur (ADEME) ; NAF 43.34Z BTP cohérent | H54: https://data.ademe.fr/datasets/liste-des-entreprises-rge-2 | I54: 43.34Z | J54: Travaux de peinture et vitrerie | K54: 21 | L54: 50 à 99 | M54: PLELO | N54: 22170 | O54: 22 | R54: Isolation des murs par l'extérieur | T54: 1994-05-26
A55: 834288086 | B55: BARDAGE INDUSTRIEL BRETAGNE | C55: Confirmé | D55: Couvreur / étancheur faisant du bardage | F55: BODACC (activité déclarée au greffe) | G55: activité déclarée : tous travaux d'entreprise de bardage, d'étanchéité, d'isolation et de pose de tour d'accès / Gestion de participations et gestion administrative comptable et techniques. | H55: https://www.bodacc.fr/ (SIREN 834288086) | I55: 43.99A | J55: Travaux d'étanchéification | K55: 03 | L55: 6 à 9 | M55: MERDRIGNAC | N55: 22230 | O55: 22 | S55: tous travaux d'entreprise de bardage, d'étanchéité, d'isolation et de pose de tour d'accès / Gestion de participations et gestion administrative comptable et techniques. | T55: 2017-12-01
A56: 501818462 | B56: CINQUIEME FACADE | C56: Confirmé | D56: Façadier (ravalement, enduits, ITE, bardage) | F56: automatique (RGE ADEME / site web) | G56: RGE isolation des murs par l'extérieur (ADEME) ; mot-clé dans le nom/enseigne ; NAF 43.91B BTP cohérent | H56: https://data.ademe.fr/datasets/liste-des-entreprises-rge-2 | I56: 43.91B | J56: Travaux de couverture par éléments | K56: 11 | L56: 10 à 19 | M56: QUESSOY | N56: 22120 | O56: 22 | R56: Fenêtres de toit | Isolation des murs par l'extérieur | Isolation des toitures terrasses ou des toitures par l'extérieur | S56: COUVERTURE, ZINGUERIE, CHARPENTE, ETANCHEITES, BARDAGES. | T56: 2008-01-07
A57: 750080137 | B57: DB FACADE | C57: Confirmé | D57: Façadier (ravalement, enduits, ITE, bardage) | F57: automatique (RGE ADEME / site web) | G57: RGE isolation des murs par l'extérieur (ADEME) ; mot-clé dans le nom/enseigne ; NAF 43.31Z BTP cohérent | H57: https://data.ademe.fr/datasets/liste-des-entreprises-rge-2 | I57: 43.31Z | J57: Travaux de plâtrerie | K57: 12 | L57: 20 à 49 | M57: SAINT-CARREUC | N57: 22150 | O57: 22 | R57: Isolation des murs par l'extérieur | S57: pose et application d'enduit | T57: 2011-10-01
A58: 849408901 | B58: L'HENORET | C58: Confirmé | D58: Façadier (ravalement, enduits, ITE, bardage) | F58: automatique (RGE ADEME / site web) | G58: RGE isolation des murs par l'extérieur (ADEME) ; site web : facade, isolation exterieur, isolation thermique par l'exterieur, ite, ravalement ; NAF 43.99C BTP cohérent | H58: https://data.ademe.fr/datasets/liste-des-entreprises-rge-2 | I58: 43.99C | J58: Travaux de maçonnerie générale et gros œuvre de bâtiment | K58: 12 | L58: 20 à 49 | M58: TREGUEUX | N58: 22950 | O58: 22 | R58: Isolation des murs par l'extérieur | Isolation des planchers bas | Isolation des toitures terrasses ou des toitures par l'extérieur | S58: Ravalement de façade, peinture, décoration, isolation thermique extérieure, étanchéité, la participation de la Société, par tous moyens, directement ou indirectement, dans toutes opérations pouvant se rattacher à son objet par voie de création de sociétés nouvelles, d'apport, de souscription ou d'achat de titres ou droits sociaux, de fusion ou autrement, de création, d'acquisition, de location, d | T58: 2019-03-01
A59: 878468545 | B59: LE GUEN PEINTURE | C59: Confirmé | D59: Façadier (ravalement, enduits, ITE, bardage) | F59: automatique (RGE ADEME / site web) | G59: RGE isolation des murs par l'extérieur (ADEME) ; site web : facade, isolation exterieur, ravalement ; NAF 43.34Z BTP cohérent | H59: https://data.ademe.fr/datasets/liste-des-entreprises-rge-2 | I59: 43.34Z | J59: Travaux de peinture et vitrerie | K59: 12 | L59: 20 à 49 | M59: PLELO | N59: 22170 | O59: 22 | R59: Isolation des murs par l'extérieur | S59: la peinture, la décoration, l'isolation thermique extérieurement, le marquage de parking, le ravalement | T59: 2019-10-24
A60: 827733619 | B60: M.R FACADES | C60: Confirmé | D60: Façadier (ravalement, enduits, ITE, bardage) | F60: automatique (RGE ADEME / site web) | G60: RGE isolation des murs par l'extérieur (ADEME) ; mot-clé dans le nom/enseigne ; NAF 43.99C BTP cohérent | H60: https://data.ademe.fr/datasets/liste-des-entreprises-rge-2 | I60: 43.99C | J60: Travaux de maçonnerie générale et gros œuvre de bâtiment | K60: 03 | L60: 6 à 9 | M60: PLAINTEL | N60: 22940 | O60: 22 | R60: Isolation des murs par l'extérieur | T60: 2017-03-01
A61: 437947237 | B61: MANUEL DIAS ENTREPRISE DE RAVALEMENT | C61: Confirmé | D61: Façadier (ravalement, enduits, ITE, bardage) | F61: automatique (RGE ADEME / site web) | G61: RGE isolation des murs par l'extérieur (ADEME) ; mot-clé dans le nom/enseigne ; NAF 43.99C BTP cohérent | H61: https://data.ademe.fr/datasets/liste-des-entreprises-rge-2 | I61: 43.99C | J61: Travaux de maçonnerie générale et gros œuvre de bâtiment | K61: 03 | L61: 6 à 9 | M61: PLEDRAN | N61: 22960 | O61: 22 | R61: Isolation des murs par l'extérieur | T61: 2001-06-01
A62: 326614823 | B62: RIVAS | C62: Confirmé | D62: Façadier (ravalement, enduits, ITE, bardage) | F62: automatique (RGE ADEME / site web) | G62: RGE isolation des murs par l'extérieur (ADEME) ; site web : enduit, facade, isolation exterieur, ravalement ; NAF 43.99C BTP cohérent | H62: https://data.ademe.fr/datasets/liste-des-entreprises-rge-2 | I62: 43.99C | J62: Travaux de maçonnerie générale et gros œuvre de bâtiment | K62: 11 | L62: 10 à 19 | M62: TREGUEUX | N62: 22950 | O62: 22 | R62: Isolation des murs par l'extérieur | T62: 1978-01-01
A63: 380081109 | B63: SARL PERSON (PERSON PARQUETS - PERSON RENOVATION FACADES ET TOITURES) | C63: Confirmé | D63: Façadier (ravalement, enduits, ITE, bardage) | F63: recherche web (agent IA) | G63: rénovation de façades et toitures (aérogommage) + parquets, 18 salariés (NAF nettoyage) | H63: https://www.mairie.biz/entreprise-person-renovation-facades-et-toitures-38329.html | I63: 81.21Z | J63: Nettoyage courant des bâtiments | K63: 11 | L63: 10 à 19 | M63: LANGROLAY-SUR-RANCE | N63: 22490 | O63: 22 | T63: 1990-11-01
A64: 450613773 | B64: FACADE 24 V.J. | C64: Confirmé | D64: Façadier (ravalement, enduits, ITE, bardage) | F64: recherche web (agent IA) | G64: ravalement, enduits, rejointoiement, ITE | H64: https://www.ravalementfacade24.fr/ | I64: 43.39Z | J64: Autres travaux de finition | K64: 11 | L64: 10 à 19 | M64: LA ROCHE CHALAIS | N64: 24490 | O64: 24 | T64: 2003-10-01
A65: 443843420 | B65: TERRIEN FACADES S.A.R.L | C65: Confirmé | D65: Façadier (ravalement, enduits, ITE, bardage) | F65: recherche web (agent IA) | G65: ravalement, bardage, peinture extérieure | H65: https://www.pagesjaunes.fr/pros/02343695 | I65: 43.99C | J65: Travaux de maçonnerie générale et gros œuvre de bâtiment | K65: 11 | L65: 10 à 19 | M65: SAINT-LAURENT-DES-HOMMES | N65: 24400 | O65: 24 | S65: Maçonnerie avec spécialité façades y compris tous travaux courants de vrd maçonnerie béton armé couverture carrelage peinture | T65: 2002-10-01
A66: 504506601 | B66: FACADES BISONTINES | C66: Confirmé | D66: Façadier (ravalement, enduits, ITE, bardage) | F66: automatique (RGE ADEME / site web) | G66: RGE isolation des murs par l'extérieur (ADEME) ; mot-clé dans le nom/enseigne ; NAF 43.34Z BTP cohérent | H66: https://data.ademe.fr/datasets/liste-des-entreprises-rge-2 | I66: 43.34Z | J66: Travaux de peinture et vitrerie | K66: 12 | L66: 20 à 49 | M66: CHATILLON-LE-DUC | N66: 25870 | O66: 25 | R66: Isolation des murs par l'extérieur | Isolation des planchers bas | S66: Tous travaux d'entretien de rénovation de façades extérieures pour tous types de bâtiment travaux de ravalement posé de tous revêtements enduits crépis tous travaux d'Echanteite sur façades mûrs extérieurs terrasses. | T66: 2008-06-01
A67: 450853486 | B67: PREVALET FACADES | C67: Confirmé | D67: Façadier (ravalement, enduits, ITE, bardage) | F67: automatique (RGE ADEME / site web) | G67: RGE isolation des murs par l'extérieur (ADEME) ; site web : crepi, facade, isolation exterieur, isolation par l'exterieur, ravalement ; mot-clé dans le nom/enseigne ; NAF 43.31Z BTP cohérent | H67: https://data.ademe.fr/datasets/liste-des-entreprises-rge-2 | I67: 43.31Z | J67: Travaux de plâtrerie | K67: 03 | L67: 6 à 9 | M67: DOMMARTIN | N67: 25300 | O67: 25 | R67: Isolation des murs par l'extérieur | Isolation par l'intérieur des murs ou rampants de toitures ou plafonds | S67: Plâtrerie peinture isolation extérieure et intérieure façades | T67: 2003-12-01
A68: 347570822 | B68: RAVALEMENT PROJECTION ISOLATION (RPI) | C68: Confirmé | D68: Façadier (ravalement, enduits, ITE, bardage) | F68: automatique (RGE ADEME / site web) | G68: RGE isolation des murs par l'extérieur (ADEME) ; mot-clé dans le nom/enseigne ; NAF 43.99C BTP cohérent | H68: https://data.ademe.fr/datasets/liste-des-entreprises-rge-2 | I68: 43.99C | J68: Travaux de maçonnerie générale et gros œuvre de bâtiment | K68: 03 | L68: 6 à 9 | M68: AVANNE-AVENEY | N68: 25720 | O68: 25 | R68: Isolation des murs par l'extérieur | Isolation des planchers bas | T68: 1988-07-01
A69: 809169311 | B69: AMELIORA (AMELIORA FACADE) | C69: Confirmé | D69: Façadier (ravalement, enduits, ITE, bardage) | F69: recherche web (agent IA) | G69: enseigne AMELIORA FACADE : ravalement, bardage, ITE (RGE) | H69: https://www.pagesjaunes.fr/pros/60329978 | I69: 43.99C | J69: Travaux de maçonnerie générale et gros œuvre de bâtiment | K69: 11 | L69: 10 à 19 | M69: BOURG-LES-VALENCE | N69: 26500 | O69: 26 | S69: Tous travaux de ravalement de façades, de bardage, de peinture, d'isolation (plâtrerie et pose de cloisons sèches) tous travaux de finition en bâtiment (neuf et rénovation). | T69: 2015-01-01
A70: 353623887 | B70: BATIMENTS PEINTURES ISOLATIONS FACADES (BPI FACADES) (BPI FACADES) | C70: Confirmé | D70: Façadier (ravalement, enduits, ITE, bardage) | F70: automatique (RGE ADEME / site web) | G70: RGE isolation des murs par l'extérieur (ADEME) ; site web : facade, facadier, isolation exterieur, isolation par l'exterieur, ite, ravalement ; mot-clé dans le nom/enseigne ; NAF 43.29A BTP cohérent | H70: https://data.ademe.fr/datasets/liste-des-entreprises-rge-2 | I70: 43.29A | J70: Travaux d'isolation | K70: 12 | L70: 20 à 49 | M70: ROMANS-SUR-ISERE | N70: 26100 | O70: 26 | R70: Isolation des murs par l'extérieur | Isolation des planchers bas | T70: 1990-01-02
A71: 820747830 | B71: FACADES DES COLLINES (FACADES DES COLLINES) | C71: Confirmé | D71: Façadier (ravalement, enduits, ITE, bardage) | F71: automatique (RGE ADEME / site web) | G71: RGE isolation des murs par l'extérieur (ADEME) ; site web : facade, isolation par l'exterieur, ravalement ; mot-clé dans le nom/enseigne ; NAF 43.31Z BTP cohérent | H71: https://data.ademe.fr/datasets/liste-des-entreprises-rge-2 | I71: 43.31Z | J71: Travaux de plâtrerie | K71: 03 | L71: 6 à 9 | M71: BOURG-DE-PEAGE | N71: 26300 | O71: 26 | R71: Isolation des murs par l'extérieur | S71: Tous travaux de plâtrerie et de finition ravalement de façades peinture et pose de plaques de plâtre | T71: 2016-06-01
A72: 832569255 | B72: GO FACADES | C72: Confirmé | D72: Façadier (ravalement, enduits, ITE, bardage) | F72: automatique (RGE ADEME / site web) | G72: RGE isolation des murs par l'extérieur (ADEME) ; site web : bardage, enduit, facade, facadier, isolation exterieur, ite, ravalement ; mot-clé dans le nom/enseigne ; NAF 43.99C BTP cohérent | H72: https://data.ademe.fr/datasets/liste-des-entreprises-rge-2 | I72: 43.99C | J72: Travaux de maçonnerie générale et gros œuvre de bâtiment | K72: 03 | L72: 6 à 9 | M72: ANDANCETTE | N72: 26140 | O72: 26 | R72: Isolation des combles perdus | Isolation des murs par l'extérieur | Isolation des planchers bas | Isolation par l'intérieur des murs ou rampants de toitures ou plafonds | T72: 2017-10-10
A73: 825294176 | B73: LES FACADES DU SOLEIL | C73: Confirmé | D73: Façadier (ravalement, enduits, ITE, bardage) | F73: automatique (RGE ADEME / site web) | G73: RGE isolation des murs par l'extérieur (ADEME) ; site web : crepi, enduit, facade, facadier, isolation exterieur, isolation par l'exterieur, ite, ravalement ; mot-clé dans le nom/enseigne ; NAF 43.29A BTP cohérent | H73: https://data.ademe.fr/datasets/liste-des-entreprises-rge-2 | I73: 43.29A | J73: Travaux d'isolation | K73: 03 | L73: 6 à 9 | M73: PORTES-LES-VALENCE | N73: 26800 | O73: 26 | R73: Isolation des murs par l'extérieur | Isolation des planchers bas | S73: Enduits hydrauliques; isolation par l'extérieur; peinture intérieure / extérieure; travaux de petite maçonnerie. | T73: 2017-01-12
A74: 510525702 | B74: MANENT FACADES V.R.C | C74: Confirmé | D74: Façadier (ravalement, enduits, ITE, bardage) | F74: automatique (RGE ADEME / site web) | G74: RGE isolation des murs par l'extérieur (ADEME) ; mot-clé dans le nom/enseigne ; NAF 43.99D BTP cohérent | H74: https://data.ademe.fr/datasets/liste-des-entreprises-rge-2 | I74: 43.99D | J74: Autres travaux spécialisés de construction | K74: 03 | L74: 6 à 9 | M74: MONTBOUCHER-SUR-JABRON | N74: 26740 | O74: 26 | R74: Isolation des murs par l'extérieur | S74: Tous travaux de façades, peinture et par extension tous travaux de maçonnerie générale. | T74: 2009-03-01
A75: 492274543 | B75: MF HABILLEZ VOS FACADES | C75: Confirmé | D75: Façadier (ravalement, enduits, ITE, bardage) | E75: NE PAS PROSPECTER : plan de cession | F75: recherche web (agent IA) | G75: ravalement, enduits, bardage (devenu Indigo MF, Indigo Groupe) | H75: https://www.indigogroupe.fr/details-indigo+mf-765 | I75: 43.99C | J75: Travaux de maçonnerie générale et gros œuvre de bâtiment | K75: 12 | L75: 20 à 49 | M75: MALATAVERNE | N75: 26780 | O75: 26 | P75: Plan de cession | Q75: 2025-02-18 | T75: 2006-07-01
A76: 418293031 | B76: OLLIER FACADES | C76: Confirmé | D76: Façadier (ravalement, enduits, ITE, bardage) | F76: recherche web (agent IA) | G76: façades : enduits traditionnels et hydrauliques, nettoyage, ITE, peinture ext. | H76: https://www.pagesjaunes.fr/pros/08087473 | I76: 43.33Z | J76: Travaux de revêtement des sols et des murs | K76: 03 | L76: 6 à 9 | M76: SAINT-DONAT-SUR-L'HERBASSE | N76: 26260 | O76: 26 | T76: 1998-04-03
A77: 499436400 | B77: SARL D'EXPLOITATION BASAGAC FACADES | C77: Confirmé | D77: Façadier (ravalement, enduits, ITE, bardage) | F77: automatique (RGE ADEME / site web) | G77: RGE isolation des murs par l'extérieur (ADEME) ; site web : crepi, enduit, facade, facadier, isolation exterieur, isolation thermique par l'exterieur, ite, ravalement ; mot-clé dans le nom/enseigne ; NAF 43.34Z BTP cohérent | H77: https://data.ademe.fr/datasets/liste-des-entreprises-rge-2 | I77: 43.34Z | J77: Travaux de peinture et vitrerie | K77: 03 | L77: 6 à 9 | M77: CHABEUIL | N77: 26120 | O77: 26 | R77: Isolation des murs par l'extérieur | T77: 2007-09-01
A78: 500696315 | B78: SUN FACADES (SUN FACADES - SUN HABITAT) | C78: Confirmé | D78: Façadier (ravalement, enduits, ITE, bardage) | F78: automatique (RGE ADEME / site web) | G78: RGE isolation des murs par l'extérieur (ADEME) ; site web : facade, facadier, isolation thermique exterieur, isolation thermique par l'exterieur, ite, ravalement ; mot-clé dans le nom/enseigne ; NAF 43.29A BTP cohérent | H78: https://data.ademe.fr/datasets/liste-des-entreprises-rge-2 | I78: 43.29A | J78: Travaux d'isolation | K78: 12 | L78: 20 à 49 | M78: BOURG-LES-VALENCE | N78: 26500 | O78: 26 | R78: Isolation des combles perdus | Isolation des murs par l'extérieur | Isolation des planchers bas | Isolation par l'intérieur des murs ou rampants de toitures ou plafonds | T78: 2007-10-08
A79: 877864934 | B79: FACADES CONCEPT | C79: Confirmé | D79: Façadier (ravalement, enduits, ITE, bardage) | F79: recherche web (agent IA) | G79: RGE isolation des murs par l'extérieur (fiche annuaire RGE) ; homonyme CONCEPT FACADE à ne pas confondre | H79: https://www.france-artisan.fr/annuaire-rge/entreprise/87786493400030 | I79: 43.99C | J79: Travaux de maçonnerie générale et gros œuvre de bâtiment | K79: 12 | L79: 20 à 49 | M79: VAL-DE-REUIL | N79: 27100 | O79: 27 | S79: entreprise générale de bâtiment, revêtement de façade / entreprise générale de bâtiment, location d'échafaudage. | T79: 2019-09-25
A80: 534317037 | B80: PROTEC FACADE | C80: Confirmé | D80: Façadier (ravalement, enduits, ITE, bardage) | F80: automatique (RGE ADEME / site web) | G80: RGE isolation des murs par l'extérieur (ADEME) ; mot-clé dans le nom/enseigne ; NAF 43.99C BTP cohérent | H80: https://data.ademe.fr/datasets/liste-des-entreprises-rge-2 | I80: 43.99C | J80: Travaux de maçonnerie générale et gros œuvre de bâtiment | K80: 03 | L80: 6 à 9 | M80: SAINT-PIERRE-LA-GARENNE | N80: 27600 | O80: 27 | R80: Isolation des murs par l'extérieur | S80: le ravalement de façade en neuf et rénovation, la maçonnerie béton armée, la pose de carrelage et de menuiserie, la peinture en bâtiment. | T80: 2011-08-29
A81: 897837720 | B81: MAD ISO BARDAGE | C81: Confirmé | D81: Façadier (ravalement, enduits, ITE, bardage) | F81: automatique (RGE ADEME / site web) | G81: RGE isolation des murs par l'extérieur (ADEME) ; mot-clé dans le nom/enseigne ; NAF 43.29A BTP cohérent | H81: https://data.ademe.fr/datasets/liste-des-entreprises-rge-2 | I81: 43.29A | J81: Travaux d'isolation | K81: 03 | L81: 6 à 9 | M81: MAINVILLIERS | N81: 28300 | O81: 28 | R81: Isolation des murs par l'extérieur | T81: 2021-02-23
A82: 509730743 | B82: SERVICE ASSISTANCE BARDAGE ETANCHEITE (SABE) | C82: Confirmé | D82: Couvreur / étancheur faisant du bardage | E82: NE PAS PROSPECTER : liquidation judiciaire | F82: BODACC (activité déclarée au greffe) | G82: activité déclarée : Bardage étanchéité | H82: https://www.bodacc.fr/ (SIREN 509730743) | I82: 43.99A | J82: Travaux d'étanchéification | K82: 03 | L82: 6 à 9 | M82: LES VILLAGES VOVEENS | N82: 28150 | O82: 28 | P82: Liquidation judiciaire | Q82: 2025-12-11 | S82: Bardage étanchéité | T82: 2009-01-07
A83: 489752865 | B83: FACADES CONCEPT | C83: Confirmé | D83: Façadier (ravalement, enduits, ITE, bardage) | F83: automatique (RGE ADEME / site web) | G83: RGE isolation des murs par l'extérieur (ADEME) ; site web : enduit, facade, isolation exterieur, ite, ravalement ; mot-clé dans le nom/enseigne ; NAF 43.39Z BTP cohérent | H83: https://data.ademe.fr/datasets/liste-des-entreprises-rge-2 | I83: 43.39Z | J83: Autres travaux de finition | K83: 21 | L83: 50 à 99 | M83: LOPERHET | N83: 29470 | O83: 29 | R83: Isolation des murs par l'extérieur | T83: 2006-04-10
A84: 813758810 | B84: SOCIETE TALOC FABRICE (TALOC PEINTURE) | C84: Confirmé | D84: Façadier (ravalement, enduits, ITE, bardage) | F84: recherche web (agent IA) | G84: peinture + rénovation de façades (Taloc Façades & Peinture) | H84: https://taloc-facades-et-peinture.vertikal.fr/ | I84: 43.34Z | J84: Travaux de peinture et vitrerie | K84: 03 | L84: 6 à 9 | M84: PLOUDALMEZEAU | N84: 29830 | O84: 29 | T84: 2015-10-01
A85: 481615490 | B85: DRISS TIZMART (DST PLATRE FACADES) | C85: Confirmé | D85: Façadier (ravalement, enduits, ITE, bardage) | F85: recherche web (agent IA) | G85: entrepreneur individuel, enseigne DST PLATRE FACADES : ravalement (annuaire) ; activité reprise en 2014 sous le même SIREN (nouvel établissement, INSEE) | H85: https://fr.mappy.com/poi/6606480345446c544deaa9d3 | I85: 43.31Z | J85: Travaux de plâtrerie | K85: 03 | L85: 6 à 9 | M85: PORTO-VECCHIO | N85: 20137 | O85: 2A | P85: Liquidation clôturée (2010), ancienne activité | Q85: 2010-07-25 | T85: 2005-03-01
A86: 440549814 | B86: EUROPE FACADES | C86: Confirmé | D86: Façadier (ravalement, enduits, ITE, bardage) | F86: automatique (RGE ADEME / site web) | G86: RGE isolation des murs par l'extérieur (ADEME) ; mot-clé dans le nom/enseigne ; NAF 43.34Z BTP cohérent | H86: https://data.ademe.fr/datasets/liste-des-entreprises-rge-2 | I86: 43.34Z | J86: Travaux de peinture et vitrerie | K86: 11 | L86: 10 à 19 | M86: AJACCIO | N86: 20167 | O86: 2A | R86: Isolation des murs par l'extérieur | T86: 2001-12-01
A87: 818662223 | B87: SARCOBAT FACADES | C87: Confirmé | D87: Façadier (ravalement, enduits, ITE, bardage) | F87: recherche web (agent IA) | G87: façadier : ravalement, enduits, maçonnerie (Corse-du-Sud) | H87: https://annuaire-entreprises.data.gouv.fr/entreprise/818662223 (source d'origine hors ligne au 26/09/2026 : https://www.sarcobat.fr/) | I87: 43.99C | J87: Travaux de maçonnerie générale et gros œuvre de bâtiment | K87: 11 | L87: 10 à 19 | M87: SARTENE | N87: 20100 | O87: 2A | S87: Maçonnerie | T87: 2015-12-01
A88: 890678600 | B88: LUCCIANA FACADES | C88: Confirmé | D88: Façadier (ravalement, enduits, ITE, bardage) | F88: recherche web (agent IA) | G88: objet social : maçonnerie et rénovation, notamment façades | H88: https://www.ravalement-de-facade.com/entreprise/lucciana-facades-890678600/ | I88: 43.99C | J88: Travaux de maçonnerie générale et gros œuvre de bâtiment | K88: 03 | L88: 6 à 9 | M88: VESCOVATO | N88: 20215 | O88: 2B | S88: Tous Tavaux de maçonnerie générale, rénovation, entretien en bâtiment notamment en façades et assimilés | T88: 2020-11-02
A89: 792660813 | B89: SARL C.V. FACADES | C89: Confirmé | D89: Façadier (ravalement, enduits, ITE, bardage) | F89: recherche web (agent IA) | G89: objet social : enduits, crépis sur tous bâtiments | H89: https://www.pagesjaunes.fr/pros/62142582 | I89: 43.99C | J89: Travaux de maçonnerie générale et gros œuvre de bâtiment | K89: 03 | L89: 6 à 9 | M89: BORGO | N89: 20290 | O89: 2B | S89: L'application de produits de revêtement (enduits, crépis...) Sur tous type de bâtiment ainsi que les petits travaux de maçonnerie. | T89: 2013-04-18
A90: 894351055 | B90: ART FACADE ENVIRONNEMENT | C90: Confirmé | D90: Façadier (ravalement, enduits, ITE, bardage) | F90: automatique (RGE ADEME / site web) | G90: RGE isolation des murs par l'extérieur (ADEME) ; site web : enduit, facade, isolation exterieur, isolation thermique par l'exterieur, ite, ravalement ; mot-clé dans le nom/enseigne ; NAF 43.99C BTP cohérent | H90: https://data.ademe.fr/datasets/liste-des-entreprises-rge-2 | I90: 43.99C | J90: Travaux de maçonnerie générale et gros œuvre de bâtiment | K90: 03 | L90: 6 à 9 | M90: SAINT-GENIES-DE-COMOLAS | N90: 30150 | O90: 30 | R90: Isolation des combles perdus | Isolation des murs par l'extérieur | S90: Pose de façade, isolation ; Maçonnerie générale. | T90: 2021-02-09
A91: 448413989 | B91: EXTREMES FACADES | C91: Confirmé | D91: Façadier (ravalement, enduits, ITE, bardage) | F91: automatique (RGE ADEME / site web) | G91: RGE isolation des murs par l'extérieur (ADEME) ; site web : facade, facadier, isolation par l'exterieur, isolation thermique par l'exterieur, ite, ravalement ; mot-clé dans le nom/enseigne ; NAF 43.34Z BTP cohérent | H91: https://data.ademe.fr/datasets/liste-des-entreprises-rge-2 | I91: 43.34Z | J91: Travaux de peinture et vitrerie | K91: 03 | L91: 6 à 9 | M91: NIMES | N91: 30900 | O91: 30 | R91: Isolation des combles perdus | Isolation des murs par l'extérieur | T91: 2003-04-28
A92: 484282744 | B92: FACADES CHAARANE (FACADES CHAARANE) | C92: Confirmé | D92: Façadier (ravalement, enduits, ITE, bardage) | F92: automatique (RGE ADEME / site web) | G92: RGE isolation des murs par l'extérieur (ADEME) ; mot-clé dans le nom/enseigne ; NAF 43.99C BTP cohérent | H92: https://data.ademe.fr/datasets/liste-des-entreprises-rge-2 | I92: 43.99C | J92: Travaux de maçonnerie générale et gros œuvre de bâtiment | K92: 12 | L92: 20 à 49 | M92: VAUVERT | N92: 30600 | O92: 30 | R92: Isolation des murs par l'extérieur | T92: 2005-09-27
A93: 448445940 | B93: FACADES LANGUEDOCIENNES LAASRI (TOUS TRAVAUX DE FACADES, ENDUIT MONOCOUCHE, RAVALEMENT TRADITIONNEL, T) | C93: Confirmé | D93: Façadier (ravalement, enduits, ITE, bardage) | F93: automatique (RGE ADEME / site web) | G93: RGE isolation des murs par l'extérieur (ADEME) ; site web : bardage, facade, facadier, isolation exterieur, ite, ravalement ; mot-clé dans le nom/enseigne ; NAF 43.99C BTP cohérent | H93: https://data.ademe.fr/datasets/liste-des-entreprises-rge-2 | I93: 43.99C | J93: Travaux de maçonnerie générale et gros œuvre de bâtiment | K93: 03 | L93: 6 à 9 | M93: UCHAUD | N93: 30620 | O93: 30 | R93: Fenêtres, volets, portes donnant sur l'extérieur | Isolation des combles perdus | Isolation des murs par l'extérieur | Isolation des planchers bas | Isolation par l'intérieur des murs ou rampants de toitures ou plafonds | T93: 2003-04-15
A94: 828476929 | B94: GARD FACADES | C94: Confirmé | D94: Façadier (ravalement, enduits, ITE, bardage) | F94: recherche web (agent IA) | G94: ravalement de façades (nettoyage, fissures, peinture) | H94: https://www.pagesjaunes.fr/pros/57129310 | I94: 43.99C | J94: Travaux de maçonnerie générale et gros œuvre de bâtiment | K94: 03 | L94: 6 à 9 | M94: BAGNOLS-SUR-CEZE | N94: 30200 | O94: 30 | S94: Tous travaux de façades et de revêtement. | T94: 2017-03-20
A95: 815225693 | B95: LG FACADES | C95: Confirmé | D95: Façadier (ravalement, enduits, ITE, bardage) | F95: automatique (RGE ADEME / site web) | G95: RGE isolation des murs par l'extérieur (ADEME) ; mot-clé dans le nom/enseigne ; NAF 43.99C BTP cohérent | H95: https://data.ademe.fr/datasets/liste-des-entreprises-rge-2 | I95: 43.99C | J95: Travaux de maçonnerie générale et gros œuvre de bâtiment | K95: 11 | L95: 10 à 19 | M95: SAINT-CHAPTES | N95: 30190 | O95: 30 | R95: Isolation des murs par l'extérieur | T95: 2016-01-04
A96: 443431614 | B96: RD21 RAVALEMENT DECORATION | C96: Confirmé | D96: Façadier (ravalement, enduits, ITE, bardage) | F96: automatique (RGE ADEME / site web) | G96: RGE isolation des murs par l'extérieur (ADEME) ; site web : crepi, enduit, facade, isolation exterieur, ite, ravalement ; mot-clé dans le nom/enseigne ; NAF 43.99C BTP cohérent | H96: https://data.ademe.fr/datasets/liste-des-entreprises-rge-2 | I96: 43.99C | J96: Travaux de maçonnerie générale et gros œuvre de bâtiment | K96: 12 | L96: 20 à 49 | M96: NIMES | N96: 30900 | O96: 30 | R96: Isolation des murs par l'extérieur | T96: 2002-10-01
A97: 533835260 | B97: SAINT GENIES BATIMENT FACADES - SGBF (SGBF) | C97: Confirmé | D97: Façadier (ravalement, enduits, ITE, bardage) | E97: Vigilance : sauvegarde en cours | F97: recherche web (agent IA) | G97: réhabilitation de façades, ITE | H97: https://www.pagesjaunes.fr/pros/55608996 | I97: 43.99C | J97: Travaux de maçonnerie générale et gros œuvre de bâtiment | K97: 11 | L97: 10 à 19 | M97: SAINT-GENIES-DE-MALGOIRES | N97: 30190 | O97: 30 | P97: Sauvegarde | Q97: 2026-02-13 | T97: 2011-07-01
A98: 539606475 | B98: SAS ETUDE TECHNIQUE ET REALISATION DES FACADES | C98: Confirmé | D98: Façadier (ravalement, enduits, ITE, bardage) | F98: automatique (RGE ADEME / site web) | G98: site web : enduit, facade, ite, ravalement ; mot-clé dans le nom/enseigne ; NAF 43.99C BTP cohérent | H98: http://www.etr-facades.fr | I98: 43.99C | J98: Travaux de maçonnerie générale et gros œuvre de bâtiment | K98: 11 | L98: 10 à 19 | M98: NIMES | N98: 30900 | O98: 30 | R98: Isolation des toitures terrasses ou des toitures par l'extérieur | T98: 2012-01-19
A99: 484480546 | B99: TRENQUIER FACADES ISOLATION (TRENQUIER FACADES ISOLATION) | C99: Confirmé | D99: Façadier (ravalement, enduits, ITE, bardage) | F99: automatique (RGE ADEME / site web) | G99: RGE isolation des murs par l'extérieur (ADEME) ; mot-clé dans le nom/enseigne ; NAF 43.34Z BTP cohérent | H99: https://data.ademe.fr/datasets/liste-des-entreprises-rge-2 | I99: 43.34Z | J99: Travaux de peinture et vitrerie | K99: 11 | L99: 10 à 19 | M99: SAINT-HILAIRE-DE-BRETHMAS | N99: 30560 | O99: 30 | R99: Isolation des murs par l'extérieur | T99: 2005-07-01
A100: 833611585 | B100: BRL FACADES | C100: Confirmé | D100: Façadier (ravalement, enduits, ITE, bardage) | E100: Vigilance : redressement judiciaire en cours | F100: recherche web (agent IA) | G100: façadier (enduits, rénovation façade, ITE) ; EN REDRESSEMENT JUDICIAIRE | H100: https://www.brl-facades-toulouse.fr/ | I100: 43.99C | J100: Travaux de maçonnerie générale et gros œuvre de bâtiment | K100: 11 | L100: 10 à 19 | M100: TOULOUSE | N100: 31100 | O100: 31 | P100: Redressement judiciaire | Q100: 2025-10-09 | S100: L'activité d 'enduiseur de façades et la rénovation de façades, l'isolation extérieure et les travaux de gros oeuvre en maçonnerie | T100: 2017-11-27
...
